Workbook

Sheet about_section
A1: SectionId | B1: Title | C1: Text | D1: JournalId | E1: JournalTitle | F1: journal
A2: 1757 | B2: Network Bioinformatics | C2: The Network Bioinformatics section is dedicated to publishing research focused on exploring and understanding complex biological pathways and interaction networks. Led by Dr. Patrick Aloy from the Institute for Research in Biomedicine, the Network Bioinformatics section welcomes submissions in various domains of network biology, which connect interdisciplinary approaches to advance the understanding of complex biological relationships. Topics considered in the scope of this section include: Submissions should provide detailed, in-depth knowledge about the development and/or application of methodologies for exploring and extracting relevant information from biological networks. The Network Bioinformatics section does not consider submissions that lack a strong focus on the integration of network-based approaches with bioinformatics. This multidisciplinary section is at the forefront of disseminating and communicating cutting-edge scientific knowledge and impactful discoveries in the field of network biology to researchers, industry, policymakers, and the public worldwide. | D2: 1722 | E2: Frontiers in Bioinformatics | F2: =VLOOKUP(D2,分野ID!$A$2:$B$49,2,FALSE) -> #N/A
A3: 2678 | B3: Imaging and Detection | C3: The Imaging and Detection section is dedicated to publishing research focused on advancing imaging and detection technologies for lab-on-chip applications. Led by Prof. Kevin Tsia from The University of Hong Kong, the Imaging and Detection section welcomes submissions in the various domains of imaging and detection, which connect interdisciplinary research and drive innovation in lab-on-chip technologies, for applications in the areas of environmental sciences, material sciences, biomedical and clinical sciences, and more. Topics considered in the scope of this section include: Submissions should provide detailed, in-depth knowledge about the development and application of imaging and detection technologies for lab-on-a-chip systems, imaging and detection computation, and emerging lab-on-a-chip imaging and detection applications. In particular, the section welcomes submissions which support and advance Sustainable Development Goals 3 (Good Health and Well-being), 9 (Industry, Innovation and Infrastructure), and 12 (Responsible Consumption and Production). This multidisciplinary section is at the forefront of disseminating and communicating cutting-edge scientific knowledge and impactful discoveries in the field of imaging and detection to researchers, industry, policymakers, and the public worldwide. | D3: 2670 | E3: Frontiers in Lab on a Chip Technologies | F3: =VLOOKUP(D3,分野ID!$A$2:$B$49,2,FALSE) -> #N/A
A4: 1883 | B4: Networks and Communications | C4: The Networks and Communications section is dedicated to publishing research focused on advancing the understanding of computer networks and communication channels. Led by Dr. Chintha Tellambura from the Department of Electrical and Computer Engineering at the University of Alberta and Dr. Theodoros Tsiftsis from the University of Thessaly, the Networks and Communications section welcomes submissions in the various domains of computer networking and communication, which connect theoretical principles with practical applications. Topics considered in the scope of this section include: Submissions should provide detailed, in-depth knowledge about the fundamentals and applications of computer networking and communication technologies. The section welcomes submissions which support and advance the SDG: SDG 9: Industry, Innovation and Infrastructure. The Networks and Communications section does not consider submissions that lack a clear focus on network technologies, communication protocols, or related computational aspects. Studies primarily centered on non-technical fields, such as sociology, psychology, or economics, without a strong connection to networks and communications, are outside the scope of this section. However, interdisciplinary research that integrates these fields with a strong emphasis on networks and communications, and contributes to the advancement of industry, innovation, and infrastructure, may be considered. This multidisciplinary section is at the forefront of disseminating and communicating cutting-edge scientific knowledge and impactful discoveries in the field of computer networking and communication to researchers, industry, policymakers, and the public worldwide. | D4: 1511 | E4: Frontiers in Computer Science | F4: =VLOOKUP(D4,分野ID!$A$2:$B$49,2,FALSE) -> Computer Science
A5: 524 | B5: Primary Immunodeficiencies | C5: The Primary Immunodeficiencies section is dedicated to publishing research focused on understanding and addressing primary immunodeficiencies in humans. Led by Dr. Fabio Candotti from Centre Hospitalier Universitaire Vaudois (CHUV), and Dr. Isabelle Meyts from KU Leuven, the Primary Immunodeficiencies section welcomes submissions in the various domains of immunodeficiency research, which aim to enhance communication and collaboration between clinicians and investigators for the advancement of human translational and basic research. Topics considered in the scope of this section include: Submissions should provide detailed, in-depth knowledge about the various aspects of primary immunodeficiencies, ultimately contributing to the development of more specific and sustained therapies. The section welcomes submissions which support and advance the SDG: SDG 3: Good Health and Well-being. The Primary Immunodeficiencies section does not consider submissions focused on general viral infections, hepatitis, or metabolic studies, as these topics fall outside the scope of primary immunodeficiencies and related research. However, the section does welcome submissions that provide detailed, in-depth knowledge about various aspects of primary immunodeficiencies, ultimately contributing to the development of more specific and sustained therapies, and supporting the advancement of good health and well-being. While the section excludes broader infectious disease research and unrelated analytical methods, it encourages submissions that employ appropriate methodologies for the study of primary immunodeficiencies. This multidisciplinary section is at the forefront of disseminating and communicating cutting-edge scientific knowledge and impactful discoveries in the field of immunodeficiency research to researchers, industry, policymakers, and the public worldwide. | D5: 276 | E5: Frontiers in Immunology | F5: =VLOOKUP(D5,分野ID!$A$2:$B$49,2,FALSE) -> Immunology
A6: 1635 | B6: Ophthalmology | C6: The Ophthalmology section of Frontiers in Medicine publishes research that advances the understanding, diagnosis and treatment ocular diseases. Led by Prof. Jodhbir Mehta from Singapore National Eye Center, the Ophthalmology specialty welcomes submissions across all clinical subspecialities, from traditional to newer disciplines such as myopia, trauma and primary care, to ultimately improve patient care and outcomes. Topics considered in-scope for this section include: Research published in the section supports and advances SDG 3: Good Health and Well-being. Studies on the anatomy, physiology, disorders or treatment of the afferent visual pathway, higher cortical visual systems, vascular tree as regards the retina and optic nerve, pupils, eye movements and pain are out of scope for the Ophthalmology section of Frontiers in Medicine , and should instead be submitted to the Neuro-Ophthalmology section of Frontiers in Neurology . This multidisciplinary section is at the forefront of disseminating and communicating cutting-edge scientific knowledge and impactful discoveries in the field of Ophthalmology to researchers, industry, policymakers, and the public worldwide. | D6: 602 | E6: Frontiers in Medicine | F6: =VLOOKUP(D6,分野ID!$A$2:$B$49,2,FALSE) -> Medicine
A7: 61 | B7: Quantitative Psychology and Measurement | C7: The Quantitative Psychology and Measurement section is dedicated to publishing research focused on advancing best practices in quantitative methods and measurement within social and behavioral sciences. Led by Dr. Pietro Cipresso from the University of Turin, the Quantitative Psychology and Measurement section welcomes submissions in various domains of quantitative psychology, which connect theory and practice to enhance research outcomes in the social sciences. Topics considered in the scope of this section include: Submissions should provide detailed, in-depth knowledge about the application of best practices in quantitative methods and measurement to answer important questions in substantive areas of social sciences. The section welcomes submissions which support and advance the SDGs: SDG 4: Quality Education, SDG 16: Peace, Justice and Strong Institutions, and SDG 17: Partnerships for the Goals. The Quantitative Psychology and Measurement section does not consider submissions focusing solely on healthcare management, marketing and consumer behavior, public policy and governance, human resources and job satisfaction, or education and training programs without a clear connection to quantitative psychological research and measurement methodologies. This multidisciplinary section is at the forefront of disseminating and communicating cutting-edge scientific knowledge and impactful discoveries in the field of quantitative psychology to researchers, industry, policymakers, and the public worldwide. | D7: 36 | E7: Frontiers in Psychology | F7: =VLOOKUP(D7,分野ID!$A$2:$B$49,2,FALSE) -> Psychology
A8: 682 | B8: Pediatric Pulmonology | C8: The Pediatric Pulmonology section is dedicated to publishing research focused on advancing the understanding and treatment of pediatric respiratory disorders. Led by Prof Dr. Anne Chang from the Queensland Children's Hospital and Menzies School of Health Research, the Pediatric Pulmonology section welcomes submissions in the various domains of pediatric pulmonology, which aim to enhance clinical outcomes and stimulate research, particularly in under-resourced settings. Topics considered in the scope of this section include: Submissions should provide detailed, in-depth knowledge about the various aspects of pediatric pulmonology, with a focus on translational applications and novel techniques that have the potential to improve patient outcomes. In particular, the section welcomes submissions which support and advance the understanding and treatment of pediatric respiratory disorders, pediatric pulmonology, and translational applications in under-resourced settings (SDG 3: Good Health and Well-being). The Pediatric Pulmonology section does not consider submissions that lack relevance to pediatric respiratory health. This includes studies that primarily address adult populations or non-respiratory pediatric conditions. However, research that has direct implications for the diagnosis, treatment, or management of pediatric pulmonary disorders, even if not exclusively focused on pediatric populations, may be considered if it contributes to the advancement of understanding and treatment in pediatric pulmonology and supports the improvement of patient outcomes in under-resourced settings. This multidisciplinary section is at the forefront of disseminating and communicating cutting-edge scientific knowledge and impactful discoveries in the field of pediatric pulmonology to researchers, industry, policymakers, and the public worldwide. | D8: 606 | E8: Frontiers in Pediatrics | F8: =VLOOKUP(D8,分野ID!$A$2:$B$49,2,FALSE) -> Pediatrics
A9: 956 | B9: Computer Security | C9: The Computer Security section is dedicated to publishing research focused on the protection and safety of computer systems and networks. Led by Dr. Nicola Zannone from Eindhoven University of Technology, the Computer Security section welcomes submissions in the various domains of computer and network security, which connect and integrate the principles and applications within related disciplines. Topics considered in the scope of this section include: Submissions should provide detailed, in-depth knowledge about the various aspects of computer and network security, aiming to advance the understanding and application of security measures in diverse contexts. The section welcomes submissions which support and advance the SDG: SDG 9: Industry, Innovation and Infrastructure. The Computer Security section does not consider submissions that are unrelated to the field of computer security. For example, those focusing on general computer science, hardware engineering, or software development without a relevance to security aspects will not be considered. However, studies that involve the application of security measures in diverse contexts, such as financial systems, healthcare and medical systems, transportation systems, and utilities and industry, are welcome. Additionally, submissions should have a strong technical or theoretical foundation in computer security to be considered for publication. This multidisciplinary section is at the forefront of disseminating and communicating cutting-edge scientific knowledge and impactful discoveries in the field of computer and network security to researchers, industry, policymakers, and the public worldwide. | D9: 1511 | E9: Frontiers in Computer Science | F9: =VLOOKUP(D9,分野ID!$A$2:$B$49,2,FALSE) -> Computer Science
A10: 2627 | B10: Complex Physical Systems | C10: This section of Frontiers devoted to Complex Physical Systems is dedicated to the exploration of the various forms of complexity displayed by physical systems at large. Led by Prof Sauro Succi, of the Italian Institute of Technology (IIT) and Harvard University, this section welcomes submission in all domains of the physical sciences which exhibit complex behaviour and show potential for novel interdisciplinary connections. Topics considered in the scope of this section include: Submissions should provide detailed, in-depth knowledge about the interplay of multiple physical mechanisms and their implications for complex systems in physics, chemistry, and biology. In particular, the section welcomes submissions which support and advance the active and biological systems, complexity at the interface between physics and biology, complexity in quantum systems, energy-saving materials, fluid motion at all scales, glassy systems, machine-learning assisted multiscale simulations, and soft flowing matter in SDGs 7 (Affordable and Clean Energy), 9 (Industry, Innovation and Infrastructure), and 13 (Climate Action). The Complex Physical Systems section does not consider submissions that lack a clear focus on the complexity and interdisciplinary nature of physical systems. Studies that primarily address isolated aspects or conventional approaches without exploring the intricate interactions and emergent properties of complex systems, such as active and biological systems, complexity at the interface between physics and biology, complexity in quantum systems, energy-saving materials, fluid motion at all scales, glassy systems, machine-learning assisted multiscale simulations, and soft flowing matter, are outside the scope of this section. The section is not devoted to the study of complex phenomena outside the realm of physics, unless dealing with techniques developed elsewhere that can be carried on to the physics domain. The section does not accepted submissions explicitly devoted to the subjects which belong to military research. This multidisciplinary section is at the forefront of disseminating and communicating cutting-edge scientific knowledge and impactful discoveries in the field of complex physical systems to researchers, industry, policymakers, and the public worldwide. | D10: 616 | E10: Frontiers in Physics | F10: =VLOOKUP(D10,分野ID!$A$2:$B$49,2,FALSE) -> Physics
A11: 1708 | B11: Environmental & Occupational Determinants | C11: The Environmental & Occupational Determinants section is dedicated to publishing research focused on the impact of environmental and occupational factors on allergic diseases. Led by Dr. Torben Sigsgaard from Aarhus University, the Environmental & Occupational Determinants section welcomes submissions in various domains of allergy research, which explore the connections between environmental and occupational exposures and their effects on health. Topics considered in the scope of this section include: Submissions should provide detailed, in-depth knowledge about the influence of environmental and occupational factors on the development and manifestation of allergic diseases. In particular, the section welcomes submissions which support and advance the environmental and occupational determinants of allergic diseases and their impact on health, in alignment with SDG 3 (Good Health and Well-being), SDG 11 (Sustainable Cities and Communities), and SDG 13 (Climate Action). The Environmental & Occupational Determinants section does not consider studies dealing with general environmental pollutants or broader correlations between the environment and health that do not specifically focus on aerobiology and allergies. Additionally, research on clinical treatments, individual behavior, or unrelated social issues that do not contribute to understanding the impact of environmental or occupational determinants on health outcomes is outside the scope of this section. This multidisciplinary section is at the forefront of disseminating and communicating cutting-edge scientific knowledge and impactful discoveries in the field of allergy research to researchers, industry, policymakers, and the public worldwide. | D11: 1705 | E11: Frontiers in Allergy | F11: =VLOOKUP(D11,分野ID!$A$2:$B$49,2,FALSE) -> #N/A
A12: 834 | B12: Food Chemistry | C12: The Food Chemistry section is dedicated to publishing research focused on the structural and functional characterization of food components. Led by Dr. Michael Rychlik from Technical University of Munich, the Food Chemistry section welcomes submissions in various domains of food chemistry, which connect the understanding of molecular food technology to bioactivity in a broad sense. Topics considered in the scope of this section include: Submissions should provide detailed, in-depth knowledge about the structural, functional, and bioactive properties of food components and their interactions with various factors. Bioactivities reported may include sensory, nutritional, physiological, or toxicological properties. In particular, the section welcomes submissions which support and advance the Food Chemistry research and Sustainable Development Goals (SDGs) such as Zero Hunger (SDG 2), Good Health and Well-being (SDG 3), and Responsible Consumption and Production (SDG 12). The Food Chemistry section does not consider submissions focusing solely on animal studies, pharmaceuticals, or medical treatments, as these topics fall outside the scope of food chemistry and its related research areas. This multidisciplinary section is at the forefront of disseminating and communicating cutting-edge scientific knowledge and impactful discoveries in the field of food chemistry to researchers, industry, policymakers, and the public worldwide. | D12: 628 | E12: Frontiers in Nutrition | F12: =VLOOKUP(D12,分野ID!$A$2:$B$49,2,FALSE) -> Nutrition
A13: 1593 | B13: Cognitive Neuroscience | C13: The Cognitive Neuroscience section is dedicated to publishing research focused on understanding the neural basis of human cognition and behavior. Led by Dr. Lutz Jäncke from the University of Zurich, the Cognitive Neuroscience section welcomes submissions in various domains of cognitive neuroscience, which aim to integrate and cross-link research in the field. Topics considered in the scope of this section include: Submissions should provide detailed, in-depth knowledge about the neural underpinnings of human cognition and behavior. The section welcomes submissions which support and advance the SDG: SDG 3 - Good Health and Well-being and SDG 4 - Quality Education. The Cognitive Neuroscience section does not consider submissions focusing solely on medical treatment, physical therapy, nursing, or preoperative care, as these fields are beyond the scope of cognitive neuroscience research. However, studies that integrate these fields with the neural basis of cognition or human cognition-related behaviors (such as memory, attention, executive functions, perception, reasoning, decision making, emotion, motivation, movement, language, learning, hemispheric asymmetry and brain plasticity etc), particularly in the context of promoting good health and well-being or quality education, are welcome. Studies that do not primarily investigate the neural basis of cognition or cognition-related behaviors will not be considered for this section. This multidisciplinary section is at the forefront of disseminating and communicating cutting-edge scientific knowledge and impactful discoveries in the field of cognitive neuroscience to researchers, industry, policymakers, and the public worldwide. | D13: 1588 | E13: Frontiers in Human Neuroscience | F13: =VLOOKUP(D13,分野ID!$A$2:$B$49,2,FALSE) -> Human Neuroscience
... A100: 76 | B100: Mood Disorders | C100: The Mood Disorders section is dedicated to publishing research from various scientific and clinical disciplines that investigates causes and treatments of mood disorders, whether as a primary diagnosis or co-morbid with other disorders. Led by Prof. Paul Stokes from King's College London, the Mood Disorders section aims to improve lives of people with Mood Disorders by rapidly communicating and publicizing key discoveries, fostering collaborative multidisciplinary research, and providing a forum where ideas can be exchanged and debated. Topics considered in the scope of this section include, but are not limited to: Submissions should provide detailed, in-depth knowledge about the various aspects of mood disorders and/or facilitate collaboration between researchers and clinicians working in this field. The Mood Disorders section does not consider bibliographic reviews. Case Reports are required to significantly advance the field, must be completely anonymised, and should be discussed in advance of submission with the Section Chief Editor. This multidisciplinary section is at the forefront of disseminating and communicating cutting-edge scientific knowledge and impactful discoveries in the field of psychiatry to researchers, industry, policymakers, and the public worldwide. | D100: 71 | E100: Frontiers in Psychiatry | F100: =VLOOKUP(D100,分野ID!$A$2:$B$49,2,FALSE) -> Psychiatry
A101: 1077 | B101: Earth Sciences | D101: 979 | E101: Frontiers for Young Minds | F101: =VLOOKUP(D101,分野ID!$A$2:$B$49,2,FALSE) -> #N/A
A102: 2107 | B102: Thermal Science and Energy Systems | C102: The Thermal Science and Energy Systems section is dedicated to publishing research focused on experimental and simulation studies having new ideas and preliminary findings in the field of heat and mass transfer and/or fluid flow, and technologies in the thermal engineering field. Led by Dr. Omid Mahian from Ningbo University, the Thermal Science and Energy Systems section welcomes submissions in the various domains of thermal engineering, which connect interdisciplinary research to address global challenges such as climate change, sustainable development, and the UN sustainable development goals (SDGs). Special attention is paid to the latest technological breakthroughs and material innovation in the field of thermal science supporting interdisciplinary research. Topics considered in the scope of this section include: Submissions should provide detailed, in-depth knowledge about the development, analysis, and optimization of thermal systems and energy technologies. This multidisciplinary section is at the forefront of disseminating and communicating cutting-edge scientific knowledge and impactful discoveries in the field of thermal engineering to researchers, industry, policymakers, and the public worldwide. | D102: 2105 | E102: Frontiers in Thermal Engineering | F102: =VLOOKUP(D102,分野ID!$A$2:$B$49,2,FALSE) -> #N/A
A103: 2065 | B103: Cost and Resource Allocation | C103: The Cost and Resource Allocation section is dedicated to publishing research focused on innovative methodologies and applications in health economics and financing. Led by Prof Jose M Valderas from the National University of Singapore, the Cost and Resource Allocation section welcomes submissions in various domains of health economics and healthcare financing, which address challenges and solutions related to the efficient and equitable allocation of healthcare resources. This section emphasizes diverse research perspectives, including cross-cultural and non-Western contexts, as well as environmental factors that influence healthcare resource allocation. Topics considered in the scope of this section include: Submissions should provide detailed, in-depth knowledge about the efficient and equitable allocation of healthcare resources, as well as methodological challenges and solutions in health economics. In particular, the section welcomes submissions which support and advance the efficient and equitable allocation of healthcare resources, methodological challenges and solutions in health economics, and cross-cultural perspectives in relation to SDG 3 (Good Health and Well-being) and SDG 10 (Reduced Inequalities). The Cost and Resource Allocation section does not consider submissions focusing solely on clinical treatment outcomes without a fundamental basis in resource allocation strategies, healthcare economics, or policy implications. Studies that do not address the broader context of resource management in healthcare, including access to care, innovative approaches to generating evidence, financing healthcare, and disparities across different racial and ethnic groups, will be considered out of scope for this section. This multidisciplinary section is at the forefront of disseminating and communicating cutting-edge scientific knowledge and impactful discoveries in the field of health economics to researchers, industry, policymakers, and the public worldwide. | D103: 2063 | E103: Frontiers in Health Services | F103: =VLOOKUP(D103,分野ID!$A$2:$B$49,2,FALSE) -> #N/A
A104: 155 | B104: Neuro-Otology | C104: The Neuro-Otology section is dedicated to publishing research focused on advancing the understanding of neuro-otological and oto-neurological disorders and their underlying pathomechanisms and etiology, including genetics. Led by Dr. Michael Strupp from Ludwig Maximilian University of Munich, the Neuro-Otology section welcomes submissions in various domains of neuro-otology and oto-neurology. They aim to enhance the interdisciplinary collaboration of clinical and basic vestibular and audiological research, namely between ENT, neurology and audiology as well as between neurophysiology, neuroanatomy, and genetics. Topics considered in the scope of this section include: Submissions can, for instance, provide detailed, in-depth knowledge about the function and dysfunctions of the peripheral or central vestibular or audiological systems, as well as their implications for the diagnosis and treatment of vertigo, dizziness, imbalance, gait disorders, and hearing problems. The section welcomes submissions which support and advance the SDG: SDG 3: Good Health and Well-being. The Neuro-Otology section does not consider submissions focused on fields outside the scope of neuro-otological/oto-neurological studies. However, we recognize that some interdisciplinary research may indirectly contribute to the understanding of the auditory and vestibular systems. Therefore, we will evaluate submissions related to electron microscopy, materials science, or artificial neural networks on a case-by-case basis, considering their relevance and potential impact on neuro-otological research and the advancement of good health and well-being. The Neuro-Otology section does not accept Case Reports. This multidisciplinary section is at the forefront of disseminating and communicating cutting-edge scientific knowledge and impactful discoveries in the field of neuro-otology to researchers, clinicians, as well as industry, policymakers, and the public worldwide. | D104: 141 | E104: Frontiers in Neurology | F104: =VLOOKUP(D104,分野ID!$A$2:$B$49,2,FALSE) -> Neurology
A105: 3487 | B105: Bioengineering | C105: The Bioengineering section is dedicated to publishing research focused on advancing transplantation medicine through innovative bioengineering approaches. Led by Dr. Wei Tao from Harvard Medical School, the Bioengineering section welcomes submissions in the various domains of transplantation bioengineering, which connect interdisciplinary fields to address critical needs in transplantation medicine. Topics considered in the scope of this section include: Submissions should provide detailed, in-depth knowledge about innovative and effective approaches in transplantation bioengineering. In particular, the section welcomes submissions which support and advance the transplantation bioengineering, biomedical device, biomaterials, biomechanics, cellular engineering, diagnostic and bioimaging, immunoengineering, nanobiotechnology, organ engineering, regenerative medicine, and tissue engineering in relation to SDG 3 (Good Health and Well-being) and SDG 9 (Industry, Innovation, and Infrastructure). This multidisciplinary section is at the forefront of disseminating and communicating cutting-edge scientific knowledge and impactful discoveries in the field of transplantation bioengineering to researchers, industry, policymakers, and the public worldwide. | D105: 2417 | E105: Frontiers in Transplantation | F105: =VLOOKUP(D105,分野ID!$A$2:$B$49,2,FALSE) -> #N/A
A106: 2209 | B106: Molecular Mechanisms of Immune Response | C106: The Molecular Mechanisms of Immune Response section is dedicated to publishing research focused on understanding the molecular basis of immune responses in various physiological and pathological contexts. Led by Dr. Stefania Grimaudo from the University of Palermo, the Molecular Mechanisms of Immune Response section welcomes submissions in the various domains of molecular medicine, which aim to enhance the knowledge and understanding of immune response pathways and their implications in disease prevention and treatment. Topics considered in the scope of this section include: Submissions should provide detailed, in-depth knowledge about the molecular mechanisms and pathways involved in immune responses and their implications in various diseases and disorders. In particular, the section welcomes submissions which support and advance the understanding of molecular mechanisms of immune response, inflammation-mediated tissue injury, chronic disease pathogenesis, immune system disorders, and dysregulation of inflammation pathways in relation to SDG 3 (Good Health and Well-being). This multidisciplinary section is at the forefront of disseminating and communicating cutting-edge scientific knowledge and impactful discoveries in the field of molecular medicine to researchers, industry, policymakers, and the public worldwide. | D106: 2086 | E106: Frontiers in Molecular Medicine | F106: =VLOOKUP(D106,分野ID!$A$2:$B$49,2,FALSE) -> #N/A
A107: 1326 | B107: Biodiversity | D107: 979 | E107: Frontiers for Young Minds | F107: =VLOOKUP(D107,分野ID!$A$2:$B$49,2,FALSE) -> #N/A
A108: 1379 | B108: Forests and the Atmosphere | C108: The Forests and the Atmosphere section is dedicated to publishing research focused on the interactions between forests and the atmosphere across various scales under changing climate conditions. Led by Dr. Jaana Bäck from the University of Helsinki and Dr. Jörg-Peter Schnitzler from the Helmholtz Center München, Helmholtz Association of German Research Centres (HZ), the Forests and the Atmosphere section welcomes submissions in the various domains of forest and atmospheric research, which aim to enhance understanding of biosphere-atmosphere interactions and their impact on Earth's climate sensitivity. Topics considered in the scope of this section include: Submissions should provide detailed, in-depth knowledge about the complex mechanisms underlying forest-atmosphere interactions, employing state-of-the-art technology and approaches in plant and tree physiology, biogeochemistry, and process-based modeling. Interdisciplinary approaches are particularly encouraged. In particular, the section welcomes submissions which support and advance the understanding of forest-atmosphere interactions in alignment with SDGs 13 (Climate Action), 15 (Life on Land), and 17 (Partnerships for the Goals). This multidisciplinary section is at the forefront of disseminating and communicating cutting-edge scientific knowledge and impactful discoveries in the field of forest and atmospheric research to researchers, industry, policymakers, and the public worldwide. | D108: 1366 | E108: Frontiers in Forests and Global Change | F108: =VLOOKUP(D108,分野ID!$A$2:$B$49,2,FALSE) -> Forests and Global Change
A109: 2256 | B109: Construction Materials | C109: The Construction Materials section is dedicated to publishing research focused on the development and application of construction materials in infrastructure and buildings. Led by Dr. Bjorn Birgisson from the University of Georgia, the Construction Materials section welcomes submissions in the various domains of construction materials, which connect the development, processing, evaluation, applications, and performance of these materials in civil engineering. Topics considered in the scope of this section include: Submissions should provide detailed, in-depth knowledge about the development and application of construction materials in infrastructure and buildings. In particular, the section welcomes submissions which support and advance the development and application of construction materials in infrastructure and buildings, contributing to SDG 9 (Industry, Innovation, and Infrastructure) and SDG 11 (Sustainable Cities and Communities). The Construction Materials section does not consider studies centered on pure materials research, materials life cycle analysis, or non-material aspects such as project management, architectural design, or unrelated engineering disciplines. However, submissions that focus on the development, processing, evaluation, applications, and performance of construction materials in infrastructure and buildings, while also contributing to sustainable development and urban planning, are welcomed. This multidisciplinary section is at the forefront of disseminating and communicating cutting-edge scientific knowledge and impactful discoveries in the field of construction materials to researchers, industry, policymakers, and the public worldwide. | D109: 921 | E109: Frontiers in Built Environment | F109: =VLOOKUP(D109,分野ID!$A$2:$B$49,2,FALSE) -> #N/A
A110: 2334 | B110: Therapy in Gastroenterology | C110: The Therapy in Gastroenterology section is dedicated to publishing research focused on innovative treatments in gastroenterology and hepatology. Led by a team of expert researchers and clinicians, the Therapy in Gastroenterology section welcomes submissions in various domains of gastroenterology and hepatology, which aim to advance the understanding and development of novel therapeutic approaches. Topics considered in the scope of this section include: Submissions should provide detailed, in-depth knowledge about innovative treatments and interventions in gastroenterology and hepatology, with a focus on recently developed substances, endoscopic or surgical treatments, and lifestyle modifications. The section welcomes submissions which support and advance the SDG 3: Good Health and Well-being. The Therapy in Gastroenterology section does not consider submissions focusing on hospital administration, safety regulations, or general disease prevention strategies that do not directly pertain to gastroenterological conditions or therapeutic interventions. Studies without a relevance to gastroenterology or its therapeutic approaches are outside the scope of this section. This multidisciplinary section is at the forefront of disseminating and communicating cutting-edge scientific knowledge and impactful discoveries in the field of gastroenterology and hepatology to researchers, industry, policymakers, and the public worldwide. | D110: 2333 | E110: Frontiers in Gastroenterology | F110: =VLOOKUP(D110,分野ID!$A$2:$B$49,2,FALSE) -> #N/A
A111: 1623 | B111: Developmental and Reproductive Toxicology | C111: The Developmental and Reproductive Toxicology section is dedicated to publishing research focused on understanding the impact of environmental chemicals on human and animal development and reproductive health. Led by Prof. Terje Svingen from the National Food Institute, Technical University of Denmark, the Developmental and Reproductive Toxicology section welcomes submissions in various domains of toxicology, which aim to enhance our understanding of the effects of harmful chemicals on early-life development and reproductive processes. Topics considered within the scope of this section include: Submissions should provide detailed, in-depth knowledge about the effects of chemical substances on developmental and reproductive processes, with a focus on understanding the underlying mechanisms and pathways. In particular, the section welcomes submissions which support and advance the understanding of the impact of environmental chemicals on human and animal development and reproductive health, and the development of alternative testing methods (SDGs 3, 6, 12, and 15). The Developmental and Reproductive Toxicology section does not consider submissions focused on plant biology. However, studies that rely on animal testing may be considered if they have a fundamental basis in toxicology and contribute to our understanding of the impact of environmental chemicals on human and animal development and reproductive health. Studies that do not address the impact of toxicants on human development or reproduction are outside the scope of this section. This multidisciplinary section is at the forefront of disseminating and communicating cutting-edge scientific knowledge and impactful discoveries in the field of toxicology to researchers, industry, policymakers, and the public worldwide. | D111: 473 | E111: Frontiers in Toxicology | F111: =VLOOKUP(D111,分野ID!$A$2:$B$49,2,FALSE) -> #N/A
A112: 532 | B112: Alloimmunity and Transplantation | C112: The Alloimmunity and Transplantation section is dedicated to publishing research focused on advancing the understanding and management of alloimmune responses and transplantation outcomes in a precision medicine approach. Led by Dr. Antoine Toubert from Université Paris Cité, and Dr. Effie Petersdorf from Fred Hutchinson Cancer Research Center, the Alloimmunity and Transplantation section welcomes submissions in the various domains of alloimmunity and transplantation, which aim to enhance the connection between basic sciences and clinical research. Topics considered in the scope of this section include: Submissions should provide detailed, in-depth knowledge about the various aspects of alloimmunity and transplantation, aiming to improve patient outcomes and quality of life. Immunological aspects of autologous hematopoietic stem cell transplantation are also covered. In particular, the section welcomes submissions which support and advance the understanding and management of alloimmune responses and transplantation outcomes, major histocompatibility complex and immunogenetics, tolerance in an allogeneic setting, immune reconstitution after allogeneic and autologous hematopoietic stem cell transplantation, innovative immunosuppressive strategies and biotherapies, cellular therapy in the control of allogeneicity (including CAR T cells), novel donor sources and availability in organ transplantation and hematopoietic stem cell transplantation, ethics of organ and hematopoietic stem cell transplantation donation, and impact on quality of life, in line with SDG 3 (Good Health and Well-being). The Alloimmunity and Transplantation section does not consider submissions focused on DNA methylation, gene expression, tumor research, sepsis, or platelet function, as these topics fall outside the scope of alloimmunity and transplantation research. This multidisciplinary section is at the forefront of disseminating and communicating cutting-edge scientific knowledge and impactful discoveries in the field of alloimmunity and transplantation to researchers, industry, policymakers, and the public worldwide. | D112: 276 | E112: Frontiers in Immunology | F112: =VLOOKUP(D112,分野ID!$A$2:$B$49,2,FALSE) -> Immunology
A113: 822 | B113: Urban Ecology | C113: The Urban Ecology section is dedicated to publishing research focused on understanding the complex biological components and processes of urban areas. Led by Dr. Juan Diego Ibáñez-Álamo from the University of Granada, the Urban Ecology section welcomes submissions in various domains of urban ecology which connect interdisciplinary approaches to comprehend urban ecosystems. Topics considered in the scope of this section include: Submissions should provide detailed, in-depth knowledge about interactions and processes within urban ecosystems. The term “urban” can be used broadly to refer to human settlements and their transitions over a range of scales and definitions, from local political and land use/land cover–based definitions to larger geographic boundaries. We are also happy to consider studies on the translation of findings in urban ecology into practice through development and testing of solutions to urban environmental and social problems, and through innovative approaches to planning, building, and managing cities, as long as they still show a clear link to ecology. The Urban Ecology section does not consider submissions focusing purely on human health and well-being, urban planning, or socio-economic studies. Authors should mention, in the methods or acknowledgements, any Field Stations or Marine Laboratories (FSMLs) where the research was conducted or that supported the research (e.g., assisted with permitting, facilitated land or data access, provided housing accommodations or research space, granted funding, etc.). This also includes others places of scientific infrastructure (e.g., botanical gardens, national laboratories, museums). Please include the FSML’s Research Organization Registry (ROR) number if available. This multidisciplinary section is at the forefront of disseminating and communicating cutting-edge scientific knowledge and impactful discoveries in the field of urban ecology to researchers, industry, policymakers, and the public worldwide. | D113: 471 | E113: Frontiers in Ecology and Evolution | F113: =VLOOKUP(D113,分野ID!$A$2:$B$49,2,FALSE) -> Ecology and Evolution
A114: 1585 | B114: Modeling and Optimization for Decision Support | C114: The Modeling and Optimization for Decision Support section is dedicated to publishing research focused on advancing multi-criteria decision-making methods for sustainable development. Led by Dr. Jingzheng Ren from Hong Kong Polytechnic University, the Modeling and Optimization for Decision Support section welcomes submissions in various domains of multi-criteria decision-making, which facilitate sustainable-production-oriented decision-making, design, and optimization leading to a more sustainable society. Topics considered in the scope of this section include: Submissions should provide detailed, in-depth knowledge about multi-criteria decision-making for promoting cleaner production and sustainable development, with a focus on interdisciplinary subjects such as engineering, management science, and social science. In particular, the section welcomes submissions which support and advance the focus areas of Modeling and Optimization for Decision Support in promoting cleaner production, sustainable development, and interdisciplinary studies, aligning with SDGs 9 (Industry, Innovation, and Infrastructure), 12 (Responsible Consumption and Production), and 17 (Partnerships for the Goals). This multidisciplinary section is at the forefront of disseminating and communicating cutting-edge scientific knowledge and impactful discoveries in the field of multi-criteria decision-making to researchers, industry, policymakers, and the public worldwide. | D114: 1547 | E114: Frontiers in Sustainability | F114: =VLOOKUP(D114,分野ID!$A$2:$B$49,2,FALSE) -> #N/A
A115: 694 | B115: Quaternary Science, Geomorphology and Paleoenvironment | C115: The Quaternary Science, Geomorphology and Paleoenvironment section is dedicated to publishing research focused on Earth systems in the past 2.6 million years. Led by Dr. Steven Forman from Baylor University, the Quaternary Science, Geomorphology and Paleoenvironment section welcomes submissions aimed at understanding, modelling, and quantifying the spatial and temporal variations of Earth surface processes, and evaluating past environmental and climate changes of Earth systems, particularly associated with human evolution and environmental interactions from associated geomorphic, sedimentary, ice and biogenic and non-biogenic carbonate archives, particularly in reference to recent human-induced global climate change. Topics considered in the scope of this section include: In particular, the section welcomes submissions supporting and advancing SDG 13 (Climate Action), SDG 14 (Life Below Water), and SDG 15 (Life on Land). This multidisciplinary section is at the forefront of disseminating and communicating cutting-edge scientific knowledge and impactful discoveries in the field of Earth system science to researchers, industry, policymakers, and the public worldwide. | D115: 654 | E115: Frontiers in Earth Science | F115: =VLOOKUP(D115,分野ID!$A$2:$B$49,2,FALSE) -> Earth Science
A116: 1572 | B116: Quantitative Sustainability Assessment | C116: The Quantitative Sustainability Assessment section is dedicated to publishing research focused on understanding the environmental, social, and economic implications of various technologies, processes, materials, and policies for a sustainable future. Led by Dr. Maria Molinos-Senante from the Pontificia Universidad Catolica de Chile and Dr. Shabbir Gheewala from the King Mongkut's University of Technology Thonburi, the Quantitative Sustainability Assessment section welcomes submissions in the various domains of sustainability assessment, which address the challenges and complexities of the field. Topics considered in the scope of this section include: Submissions should provide detailed, in-depth knowledge about the methodology, data, or implementation aspects of quantitative sustainability assessment, addressing challenges and advancing the field through a multidisciplinary approach. In particular, the section welcomes submissions which support and advance the focus areas of the Quantitative Sustainability Assessment section and SDGs, such as responsible consumption and production (SDG 12), climate action (SDG 13), clean water and sanitation (SDG 6), affordable and clean energy (SDG 7), industry, innovation, and infrastructure (SDG 9), and sustainable cities and communities (SDG 11). This multidisciplinary section is at the forefront of disseminating and communicating cutting-edge scientific knowledge and impactful discoveries in the field of sustainability assessment to researchers, industry, policymakers, and the public worldwide. | D116: 1547 | E116: Frontiers in Sustainability | F116: =VLOOKUP(D116,分野ID!$A$2:$B$49,2,FALSE) -> #N/A
A117: 701 | B117: Molecular Diagnostics and Therapeutics | C117: The Molecular Diagnostics and Therapeutics section is dedicated to publishing research focused on the development and application of diagnostic and therapeutic tools for clinical use. Led by Prof. Matteo Becatti from the Department of Experimental and Clinical Biomedical Sciences 'Mario Serio' at the University of Firenze, the Molecular Diagnostics and Therapeutics section welcomes submissions in various domains of molecular biosciences, which connect the identification of molecular targets and biomarkers to their clinical applications. Topics considered in the scope of this section include: Submissions should provide detailed, in-depth knowledge about the molecular diagnostics and therapeutics field, focusing on the topics listed above. In particular, the section welcomes submissions which support and advance the molecular diagnostics and therapeutics, focusing on drug and diagnostic co-developments, clinical trials, personalized medicine, disease detection and monitoring, emerging molecular technologies (including the design and development of medical devices, diagnostic tools, and drug delivery systems), genetic variations, novel molecular therapies, and regulatory and ethical issues, contributing to SDGs 3 (Good Health and Well-being) and 9 (Industry, Innovation, and Infrastructure). The Molecular Diagnostics and Therapeutics section does not consider submissions related to clinical trials, medical imaging, inflammation and immune response, mental health, unless they have a strong molecular diagnostics or therapeutics component. However, the section does focus on bioinformatic studies (including artificial intelligence techniques, such as machine learning and deep learning, to analyze complex molecular data, predict disease outcomes, and optimize diagnostic and therapeutic strategies.) identifying diagnostic or prognostic markers for diseases, with in silico data supported by validating results. Studies without relevance to diagnostics or therapeutics are outside the scope of this section. This multidisciplinary section is at the forefront of disseminating and communicating cutting-edge scientific knowledge and impactful discoveries in the field of molecular biosciences to researchers, industry, policymakers, and the public worldwide. | D117: 698 | E117: Frontiers in Molecular Biosciences | F117: =VLOOKUP(D117,分野ID!$A$2:$B$49,2,FALSE) -> Molecular Biosciences
A118: 2870 | B118: ADHD | C118: The ADHD section is dedicated to publishing research focused on advancing the understanding and treatment of ADHD and related neurodevelopmental disorders. Led by Dr. Cesar Soutullo MD PhD from the University of Texas Health Science Center at Houston, the ADHD section welcomes submissions in the various domains of ADHD research, which connect fundamental findings to clinical applications and promote a comprehensive understanding of the disorder. Topics considered in the scope of this section include: Submissions should provide detailed, in-depth knowledge about the various aspects of ADHD and its management, contributing to a better understanding of the disorder and improved patient outcomes. The section welcomes submissions which support and advance the SDG: SDG 3: Good Health and Well-being. The ADHD section does not consider submissions that primarily focus on general medicine without a relevance to ADHD. Studies that do not specifically address the diagnosis, treatment, or understanding of ADHD and its related conditions are outside the scope of this section. However, submissions related to genetics are welcome as long as they have a direct relevance to ADHD, its etiology, or its management. This multidisciplinary section is at the forefront of disseminating and communicating cutting-edge scientific knowledge and impactful discoveries in the field of ADHD research to researchers, industry, policymakers, and the public worldwide. | D118: 71 | E118: Frontiers in Psychiatry | F118: =VLOOKUP(D118,分野ID!$A$2:$B$49,2,FALSE) -> Psychiatry
A119: 3048 | B119: Energy Storage | C119: The Energy Storage section is committed to publishing research centered on advancing energy storage technologies for a sustainable future. Led by Dr. Kui Jiao from Tianjin University, the Energy Storage section encourages submissions in various domains of energy storage, which aim to facilitate the transition towards carbon neutrality and large-scale renewable energy utilization. Topics of interest to the Energy Storage section especially focus on the development of battery and thermal storage materials, renewable fuels for energy storage and utilization, life cycle assessment of energy storage technologies in complex scenarios, and integration system of energy storage and fluctuant renewable sources. Topics considered within the scope of this section include: Submissions should provide comprehensive, in-depth knowledge about the development, implementation, and assessment of energy storage technologies and materials. In particular, the section welcomes submissions which support and advance the focus areas of the Section and SDGs, such as affordable and clean energy (SDG 7), industry, innovation, and infrastructure (SDG 9), and climate action (SDG 13). This multidisciplinary section is at the forefront of disseminating and communicating cutting-edge scientific knowledge and impactful discoveries in the field of Energy Storage to researchers, industry, policymakers, and the public worldwide. | D119: 626 | E119: Frontiers in Energy Research | F119: =VLOOKUP(D119,分野ID!$A$2:$B$49,2,FALSE) -> Energy Research
... A184: 2609 | B184: Cardiometabolic Health | C184: The Cardiometabolic Health section is dedicated to publishing research focused on the intricate relationship between oral and cardiometabolic health. Led by Dr. Shilpa Bhupathiraju from Harvard Medical School, the Cardiometabolic Health section welcomes submissions in various domains of oral and cardiometabolic health research, which aim to enhance the understanding of the interplay between these two areas. Topics considered in the scope of this section include: Submissions should provide detailed, in-depth knowledge about the complex connections between oral and cardiometabolic health, as well as potential interventions and preventive measures. In particular the section welcomes submissions which contribute towards SDG 3 (Good Health and Well-being). Submissions which do not relate to the various domains of oral and cardiometabolic health research may be better suited to different sections within Frontiers in Oral Health, or other Frontiers journals, such as Frontiers in Dental Medicine. This multidisciplinary section is at the forefront of disseminating and communicating cutting-edge scientific knowledge and impactful discoveries in the field of oral and cardiometabolic health research to researchers, industry, policymakers, and the public worldwide. | D184: 1702 | E184: Frontiers in Oral Health | F184: =VLOOKUP(D184,分野ID!$A$2:$B$49,2,FALSE) -> Oral Health
A185: 978 | B185: Neuroscience and Psychology | D185: 979 | E185: Frontiers for Young Minds | F185: =VLOOKUP(D185,分野ID!$A$2:$B$49,2,FALSE) -> #N/A
A186: 1726 | B186: Psycho-Oncology | C186: The Psycho-Oncology section is dedicated to publishing research focused on the multidisciplinary aspects of cancer care, addressing psychological, behavioral, social, physical, and functional dimensions. Led by Dr. Anja Mehnert from University Hospital Leipzig, the Psycho-Oncology section welcomes submissions in various domains of psycho-oncology, which connect diverse aspects of cancer care, from prevention to end-of-life support. Topics considered in the scope of this section include: Submissions should provide detailed, in-depth knowledge about the various aspects of psycho-oncology, addressing the diverse challenges faced by cancer patients, their families, and healthcare providers. In particular, the section welcomes submissions which support and advance the multidisciplinary aspects of cancer care, psychological interventions, and psychotherapy in cancer care, addressing the diverse challenges faced by cancer patients, their families, and healthcare providers, and contributing to the achievement of SDGs 3 (Good Health and Well-being) and 17 (Partnerships for the Goals). The Psycho-Oncology section does not consider submissions focusing on cell biology, childhood development, or interpersonal relationships, unless they have a relevance to the psychological aspects of cancer care, prevention, or survivorship. Studies without a relevance to the psycho-oncological context are outside the scope of this section. This multidisciplinary section is at the forefront of disseminating and communicating cutting-edge scientific knowledge and impactful discoveries in the field of psycho-oncology to researchers, industry, policymakers, and the public worldwide. | D186: 36 | E186: Frontiers in Psychology | F186: =VLOOKUP(D186,分野ID!$A$2:$B$49,2,FALSE) -> Psychology
A187: 2415 | B187: Gastrointestinal Cancers: Gastric and Esophageal Cancers | C187: The Gastrointestinal Cancers: Gastric and Esophageal Cancers section is dedicated to publishing research focused on advancing the understanding and treatment of gastric and esophageal neoplasia. Led by Dr. Liang Qiao from the Faculty of Medicine and Health at The University of Sydney, the Gastrointestinal Cancers: Gastric and Esophageal Cancers section welcomes submissions in various domains of gastrointestinal cancer research, which aim to accelerate the clinical applications of biological advances. Topics considered in the scope of this section include: Submissions should provide detailed, in-depth knowledge about the mechanisms, prevention, early detection, and treatment of gastric and esophageal neoplasia. The section welcomes submissions which support and advance the SDG: SDG 3: Good Health and Well-being. The Gastrointestinal Cancers: Gastric and Esophageal Cancers section does not consider manuscripts focusing on cancer risk factors and stratification, as these topics may not directly contribute to the understanding and treatment of gastric and esophageal neoplasia. However, the section welcomes meta-analyses and descriptive studies based on rigorous statistical methods or systematic reviews. Additionally, studies containing purely surgical procedures treating Gastric and Esophageal Cancers are excluded, unless they are directly related to the integrated treatments of advanced cancer or endoscopic identification and treatment of early neoplasia. Case reports that are not well-studied (e.g., without correlative data, diagnosis not convincingly established, no research components, etc). While studies consisting solely of bioinformatics, computational analysis, or predictions without validation are not suitable, the section does consider research on molecular, genetic, and morphological biomarkers of tumor progression. Research on cost-effectiveness, preoperative training, molecular biology unrelated to cancer, real-time systems, or surgical complications without a fundamental basis in gastric or esophageal cancer research and treatment are not covered by this section. This multidisciplinary section is at the forefront of disseminating and communicating cutting-edge scientific knowledge and impactful discoveries in the field of gastrointestinal cancer research to researchers, industry, policymakers, and the public worldwide. | D187: 451 | E187: Frontiers in Oncology | F187: =VLOOKUP(D187,分野ID!$A$2:$B$49,2,FALSE) -> Oncology
A188: 749 | B188: Colloidal Materials and Interfaces | C188: The Colloidal Materials and Interfaces section is dedicated to publishing research focused on advancing the understanding of colloid and interface science. Led by Professor Tierui Zhang from Technical Institute of Physics and Chemistry (TIPC) and Chinese Academy of Sciences (CAS), the Colloidal Materials and Interfaces section welcomes submissions in various domains of colloid and interface science, which connect fundamental concepts with practical applications. Topics considered in the scope of this section include: Submissions should provide detailed, in-depth knowledge about the synthesis, assembly, properties, and functions of colloidal materials and the processes of various interfaces. In particular, the section welcomes submissions which support and advance the understanding of colloid and interface science, colloidal solutions, self-assembly, surfactant and polymer mesophases, colloidal soft matter, membranes, coatings, films, gels, and foams, colloidal nanostructures, micro-mesoporous materials and core-shell structures, interfacial processes, adsorption, capillarity, wetting, and microfluidics, biointerfaces, biocolloids, biofilms, and biomembranes, and SDGs 9 (Industry, Innovation, and Infrastructure), 12 (Responsible Consumption and Production), and 14 (Life Below Water). The Colloidal Materials and Interfaces section does not consider studies that only make routine use of, or minor extensions to well-established methodologies, such as fitting adsorption data to common isotherm models. This multidisciplinary section is at the forefront of disseminating and communicating cutting-edge scientific knowledge and impactful discoveries in the field of colloid and interface science to researchers, industry, policymakers, and the public worldwide. | D188: 608 | E188: Frontiers in Materials | F188: =VLOOKUP(D188,分野ID!$A$2:$B$49,2,FALSE) -> Materials
A189: 1917 | B189: Molecular Mechanisms of Aging | C189: The Molecular Mechanisms of Aging section is committed to publishing research centered on exploring the fundamental processes involved in aging. Under the guidance of Prof. Consuelo Borras from the University of Valencia, this section invites submissions across various domains in the field of aging, which aim to enhance our understanding of the aging process and its underlying mechanisms. Topics considered within the scope of this section include (but are not limited to): Submissions should offer comprehensive, in-depth knowledge about the basic mechanisms of aging, contributing to our understanding of this complex process. The section welcomes submissions that support and advance the SDG: SDG 3: Good Health and Well-being. The Molecular Mechanisms of Aging does not consider studies related to processes associated with aging that do not have a direct focus on basic mechanisms, such as inflammation, metabolism, or neoplastic transformations. Additionally, research primarily centered on clinical interventions, behavioral aspects, or epidemiological data without a molecular basis is considered outside the scope of this section. However, the section welcomes submissions that support and advance the goal of promoting good health and well-being, as long as they are centered on the molecular mechanisms of aging. This multidisciplinary section is at the forefront of disseminating and communicating cutting-edge scientific knowledge and impactful discoveries in the field of Molecular Mechanisms of Aging to researchers, industry, policymakers, and the public worldwide. | D189: 1566 | E189: Frontiers in Aging | F189: =VLOOKUP(D189,分野ID!$A$2:$B$49,2,FALSE) -> #N/A
A190: 1875 | B190: Neuropathic Pain | C190: The Neuropathic Pain section of Frontiers in Pain Research publishes experimental (animal and human) and clinical studies, case series as well as review papers that discuss the epidemiology, pheno- and genotypes, etiology and novel pharmacological (and non-pharmacological) treatment options for neuropathic pain. Recent studies indicate that in the Western World approximately 1 in 5 individuals experience some form of chronic pain. This means that these people experience regular episodes of pain that exists for at least 3 months. Chronic pain has enormous psychological and socioeconomic consequences that range from the reduction of the quality of life, unemployment and social isolation to increased health care consumption and high costs to society. A large group of people with chronic pain have signs and symptoms of neuropathic pain, related to defects within the somatosensory system. These neuropathic symptoms, together considered a disease on its own, are debilitating and have a negative impact on the quality of life. Neuropathic pain is difficult to treat and, additionally, many people do not receive appropriate treatment of their symptoms due to a lack of understanding of the symptoms and causes of neuropathic pain. Hence, we do not only need to improve our understanding of the neuropathic pain syndrome but also educate our students and fellow physicians. Research efforts in this field are dedicated to educate and increase our knowledge of the complexities of neuropathic pain, in the broadest sense. We will publish experimental (animal and human) and clinical studies, as well as case series and (systematic) review papers that discuss the epidemiology, pheno- and genotypes, etiology and novel pharmacological (and non-pharmacological) treatment options for neuropathic pain. Areas covered in this section include but are not limited to: · Discussions of novel diagnostic and analyses techniques that will impact the way we will diagnose and treat our patients in the future. For example, one such promising technique is cornea confocal microscopy that allows non-invasive detection of small nerve fiber disease. · Central, peripheral and segmental sensitization · Endogenous pain modulation in chronic pain · Shared decision-making and patient-tailored medicine · Persistent postoperative pain of neuropathic etiology · Neuropathy-associated syndromes and diseases · Finally, one topic that is poorly addressed in both experimental and clinical studies is the benefit-harm relationship of individualized therapy. We welcome studies on this important topic in which benefits include efficacy or pain relief and harm relates to toxicity, abuse/addiction, sedation, respiratory depression, etc. In the end, our patients are best served by our improved ability to predict the best treatment design based on the genotyping and phenotypic makeup of their neuropathic pain disease, whilst minimizing possible adverse effects. We intend to build the specialty section “Neuropathic Pain” into a section that appeals to all with a wide interest in chronic pain in general and neuropathic pain symptoms and disease in particular. All studies must contribute insights into the mechanism, epidemiology, symptomatology, diagnosis, and treatment of neuropathic pain. Reports dealing with chronic pain outside of the broader realm of neuropathy-associated symptoms do not fall within the scope of this section and should be submitted to more general journals. | D190: 1727 | E190: Frontiers in Pain Research | F190: =VLOOKUP(D190,分野ID!$A$2:$B$49,2,FALSE) -> #N/A
A191: 1458 | B191: Planetary Health | C191: The Planetary Health section is dedicated to publishing research focused on exploring the interdependencies between human health, civilizational processes, and the Earth system. Led by Prof. Jouni Jaakkola, the Planetary Health section welcomes submissions in various domains of planetary health, which connect the understanding of human health and environmental stewardship. This section emphasizes diverse research perspectives, including cross-cultural and environmental contexts. Topics considered in the scope of this section include: Submissions should provide detailed, in-depth knowledge about the interplay between human health, civilizational processes, and the Earth system. In particular, the section welcomes submissions which support and advance the focus areas of the Section and SDGs, including good health and well-being (SDG 3), clean water and sanitation (SDG 6), affordable and clean energy (SDG 7), sustainable cities and communities (SDG 11), responsible consumption and production (SDG 12), climate action (SDG 13), life below water (SDG 14), life on land (SDG 15), and reduced inequalities (SDG 10). The Planetary Health section does not consider papers focused on simple bibliometric studies or those that are too clinically focused without relevance to public health. Additionally, while submissions solely concentrating on climate change or environmental risk assessment without a foundation in human health and well-being are outside the scope of this section, research that integrates these topics with human health and well-being will be considered. This multidisciplinary section is at the forefront of disseminating and communicating cutting-edge scientific knowledge and impactful discoveries in the field of planetary health to researchers, industry, policymakers, and the public worldwide. | D191: 609 | E191: Frontiers in Public Health | F191: =VLOOKUP(D191,分野ID!$A$2:$B$49,2,FALSE) -> Public Health
A192: 1948 | B192: Precision Livestock Farming | C192: The Precision Livestock Farming section is dedicated to publishing research focused on advancing the science and data-driven approach to monitoring and managing farm animals in various production systems. Led by Dr. Tomas Norton from KU Leuven, the Precision Livestock Farming section welcomes submissions in the various domains of animal science, which contribute to the improvement of animal production, welfare, and health while addressing sustainability and resource efficiency. Topics considered in the scope of this section include: Submissions should provide detailed, in-depth knowledge about how the technologies and techniques strengthen livestock systems with respect to UN Sustainable Development Goals and the advancement of One Health and/or One Welfare philosophies. In particular, the section welcomes submissions which support and advance the precision livestock farming, animal welfare, and sustainable resource management in alignment with SDGs 2 (Zero Hunger), 12 (Responsible Consumption and Production), and 15 (Life on Land). The Precision Livestock Farming section does not consider studies that lack a clear focus on precision technologies, methodologies, or data-driven approaches for livestock management. Research unrelated to livestock farming or without a strong connection to improving efficiency, welfare, or sustainability in the industry is outside the scope of this section. However, studies that may not directly address SDGs 2, 12, or 15 but still contribute to the overall advancement of precision livestock farming, animal welfare, and sustainable resource management will be considered. This multidisciplinary section is at the forefront of disseminating and communicating cutting-edge scientific knowledge and impactful discoveries in the field of animal science to researchers, industry, policymakers, and the public worldwide. | D192: 1719 | E192: Frontiers in Animal Science | F192: =VLOOKUP(D192,分野ID!$A$2:$B$49,2,FALSE) -> #N/A
A193: 716 | B193: Cellular Biochemistry | C193: The Cellular Biochemistry section is dedicated to publishing research focused on the biochemistry of pathophysiological processes and their underlying mechanisms. Led by Prof. Graça Soveral from the University of Lisbon, the Cellular Biochemistry section welcomes submissions in various domains of biochemistry, which connect the understanding of cellular and molecular responses to disease states and environmental triggers. Topics considered in the scope of this section include: Submissions should provide detailed, in-depth knowledge about the biochemical basis of pathophysiological processes and the various techniques used to study and manipulate biological systems. In particular, the section welcomes submissions that support and advance the cellular biochemistry, metabolism, enzymology, membrane transport, organ cross-talk, cell processes regulation, organismal development, post-translational modifications, and energy balance in relation to SDGs 3 (Good Health and Well-being). The Cellular Biochemistry section does not consider submissions focused on specific disease processes without a strong emphasis on cellular biochemistry. However, studies that investigate topics such as cancer, inflammation and immune response, obesity, liver fibrosis, lung injury, or cartilage and tissue damage with a primary focus on cellular biochemistry, metabolism, enzymology, membrane transport, organ cross-talk, cell processes regulation, organismal development, post-translational modifications, and energy balance are welcome and considered within the scope of this section. This multidisciplinary section is at the forefront of disseminating and communicating cutting-edge scientific knowledge and impactful discoveries in the field of biochemistry to researchers, industry, policymakers, and the public worldwide. | D193: 698 | E193: Frontiers in Molecular Biosciences | F193: =VLOOKUP(D193,分野ID!$A$2:$B$49,2,FALSE) -> Molecular Biosciences
A194: 1565 | B194: Nanocatalysis | C194: The Nanocatalysis section is dedicated to publishing research focused on advancing the understanding of catalysis at the nanoscale. Led by Prof. Francis Verpoort from Wuhan University of Technology, the Nanocatalysis section welcomes submissions in various domains of nanocatalysis, which aim to enhance the knowledge and application of nanoscale catalytic processes and materials. Topics considered in the scope of this section include: Submissions should provide detailed, in-depth knowledge about the development, analysis, and performance of nanocatalysts and their applications in various catalytic processes. The section welcomes submissions that support and advance the SDG: SDG 9: Industry, Innovation and Infrastructure; SDG 12: Responsible Consumption and Production. While the Nanocatalysis section is dedicated to the advancement of nanoscale catalysis, it does not cover research that is primarily focused on macro-scale catalytic processes, bulk catalysts without nanoscale features, or studies that do not provide a clear connection to nanoscale properties. Additionally, purely theoretical work without experimental validation, as well as submissions lacking significant innovation or a detailed understanding of nanocatalytic mechanisms, may be considered out of scope. This section emphasizes novel insights into nanocatalysts and their practical applications, aiming to contribute to sustainable development goals through tangible advancements in industry, innovation, and infrastructure. This multidisciplinary section is at the forefront of disseminating and communicating cutting-edge scientific knowledge and impactful discoveries in the field of nanocatalysis to researchers, industry, policymakers, and the public worldwide. | D194: 1528 | E194: Frontiers in Nanotechnology | F194: =VLOOKUP(D194,分野ID!$A$2:$B$49,2,FALSE) -> #N/A
A195: 2528 | B195: Intelligent Aerospace Systems | C195: The Intelligent Aerospace Systems section is dedicated to publishing research focused on advancing AI-driven technologies and systems in the aerospace domain. Led by Prof. Kelly Cohen from the University of Cincinnati, the Intelligent Aerospace Systems section welcomes submissions in various domains of intelligent aerospace systems, which connect innovative technologies and applications to enhance the performance and safety of aerospace operations. Topics considered in the scope of this section include: Submissions should provide detailed, in-depth knowledge about the integration of AI technologies and systems in the aerospace industry, focusing on enhancing performance, safety, and reliability. In particular, the section welcomes submissions which support and advance the intelligent aerospace systems, focusing on enhancing performance, safety, and reliability (SDG 9: Industry, Innovation and Infrastructure; SDG 11: Sustainable Cities and Communities; SDG 13: Climate Action). This multidisciplinary section is at the forefront of disseminating and communicating cutting-edge scientific knowledge and impactful discoveries in the field of intelligent aerospace systems to researchers, industry, policymakers, and the public worldwide. | D195: 2449 | E195: Frontiers in Aerospace Engineering | F195: =VLOOKUP(D195,分野ID!$A$2:$B$49,2,FALSE) -> #N/A
A196: 3233 | B196: Environmental Catalysis | C196: The Environmental Catalysis section is dedicated to publishing research focused on the study and application of catalysis in environmental processes and sustainable development. Led by Dr. Qingguo (Jack) Huang from the University of Georgia, Griffin Campus, the Environmental Catalysis section welcomes submissions in the various domains of environmental catalysis, which connect the understanding of natural and engineered systems with the goal of addressing environmental challenges. Topics considered in the scope of this section include: Submissions should provide detailed, in-depth knowledge about the role of catalysis in addressing environmental issues and promoting sustainable development. In particular, the section welcomes submissions which support and advance the environmental catalysis, pollution prevention and remediation, cleaner production, waste reduction and reuse, and sustainable development (SDGs 6, 7, 9, 11, 12, and 13). This multidisciplinary section is at the forefront of disseminating and communicating cutting-edge scientific knowledge and impactful discoveries in the field of environmental catalysis to researchers, industry, policymakers, and the public worldwide. | D196: 2851 | E196: Frontiers in Environmental Engineering | F196: =VLOOKUP(D196,分野ID!$A$2:$B$49,2,FALSE) -> #N/A
A197: 835 | B197: Smart Materials | C197: The Smart Materials section is dedicated to publishing research focused on the development and application of materials with adaptive or active responses to stimuli. Led by Professor Weihua Li from the University of Wollongong, the Smart Materials section welcomes submissions in various domains of smart materials research, which connect interdisciplinary efforts to improve existing materials and discover new ones. Topics considered in the scope of this section include: Submissions should provide detailed, in-depth knowledge about the development, improvement, and application of smart materials in various engineering systems. The section welcomes submissions which support and advance the SDG: SDG 9: Industry, Innovation and Infrastructure; SDG 12: Responsible Consumption and Production; SDG 3: Good Health and Wellbeing. The Smart Materials section does not consider submissions focused solely on optical engineering, water treatment, or energy production, unless they are directly related to the development, improvement, and application of smart materials in various engineering systems. This is to maintain our specialized focus on smart materials and their applications, while still supporting and advancing the goals of industry, innovation, infrastructure, responsible consumption, and production. This multidisciplinary section is at the forefront of disseminating and communicating cutting-edge scientific knowledge and impactful discoveries in the field of smart materials research to researchers, industry, policymakers, and the public worldwide. | D197: 608 | E197: Frontiers in Materials | F197: =VLOOKUP(D197,分野ID!$A$2:$B$49,2,FALSE) -> Materials
... A358: 2254 | B358: Radiomics and Artificial Intelligence | C358: The Radiomics and Artificial Intelligence section is dedicated to publishing research focused on the intersection of medical informatics, computational imaging, and artificial intelligence in nuclear medicine. Led by Specialty Chief Editor Professor Regina Beets-Tan from The Netherlands Cancer Institute (NKI), the Radiomics and Artificial Intelligence section welcomes submissions in various domains of nuclear medicine, which connect novel data-driven computer technologies to address clinically relevant questions. Topics considered in the scope of this section include: Submissions should provide detailed, in-depth knowledge about the role of radiomics and artificial intelligence in nuclear medicine, focusing on the listed topics to ensure relevance and specificity. The section welcomes submissions which support and advance the Sustainable Development Goal 3 (SDG 3): Good Health and Well-being and SDG 9: Industry, Innovation, and Infrastructure. The Radiomics and Artificial Intelligence section does not consider submissions that solely focus on nuclear medicine or artificial intelligence. This multidisciplinary section is at the forefront of disseminating and communicating cutting-edge scientific knowledge and impactful discoveries in the field of radiomics and artificial intelligence to researchers, industry, policymakers, and the public worldwide. | D358: 2062 | E358: Frontiers in Nuclear Medicine | F358: =VLOOKUP(D358,分野ID!$A$2:$B$49,2,FALSE) -> #N/A
A359: 1082 | B359: Human Health | D359: 979 | E359: Frontiers for Young Minds | F359: =VLOOKUP(D359,分野ID!$A$2:$B$49,2,FALSE) -> #N/A
A360: 2090 | B360: Environmental Systems Engineering | C360: The Environmental Systems Engineering section is dedicated to publishing research focused on addressing complex environmental challenges through interdisciplinary approaches. Led by Dr. Can Wang from the Tsinghua University, the Environmental Systems Engineering section welcomes submissions in the various domains of environmental systems analyses, which aim to provide sustainable solutions for intertwined environmental issues. Topics considered in the scope of this section include: Submissions should provide detailed, in-depth knowledge about the interrelationships between natural and human systems, environmental processes, and future projections of environment-economy-energy systems to support sustainable development decisions and actions. In particular, the section welcomes submissions which support and advance the Environmental Systems Engineering focus areas and SDGs, such as SDG 6 (Clean Water and Sanitation), SDG 7 (Affordable and Clean Energy), SDG 11 (Sustainable Cities and Communities), SDG 12 (Responsible Consumption and Production), SDG 13 (Climate Action), and SDG 15 (Life on Land). The Environmental Systems Engineering section does not consider studies dealing with technical environmental science and engineering that do not have a direct connection to environmental systems or their engineering applications. Additionally, submissions primarily focusing on quality control and testing methods without addressing the broader implications of these methods on environmental systems are outside the scope of this section. This multidisciplinary section is at the forefront of disseminating and communicating cutting-edge scientific knowledge and impactful discoveries in the field of environmental systems analyses to researchers, industry, policymakers, and the public worldwide. | D360: 627 | E360: Frontiers in Environmental Science | F360: =VLOOKUP(D360,分野ID!$A$2:$B$49,2,FALSE) -> Environmental Science
A361: 157 | B361: Autonomic Neuroscience | C361: The Autonomic Neuroscience section is dedicated to publishing research focused on the development, function, and dysfunction of the autonomic nervous system. Led by Professor Joel Bornstein from The University of Melbourne and Professor De-Pei Li from The University of Missouri, the Autonomic Neuroscience section welcomes submissions in various domains of autonomic neuroscience, which connect fundamental and clinical aspects of autonomic regulation and its development. The autonomic nervous system maintains homeostasis by regulating and integrating wide range of functions including blood pressure, heart rate, temperature, gastrointestinal motility, urination, and sexuality, among other essential functions. The autonomic system produces adaptive responses to physiological and pathophysiological challenges. Topics considered in the scope of this section include: Submissions should provide detailed, in-depth knowledge about the various aspects of autonomic function, including its development, dysfunction, and aging, as well as its interactions with other regulatory systems. The section welcomes submissions which support and advance the SDG: SDG 3: Good Health and Well-being. The Autonomic Neuroscience section does not consider submissions focusing on sports performance, COVID-19 research unrelated to autonomic function, or mental health without relevance to autonomic processes. Additionally, gene expression studies lacking an autonomic context and medical imaging research without relevance to autonomic neuroscience are excluded from consideration. This multidisciplinary section is at the forefront of disseminating and communicating cutting-edge scientific knowledge and impactful discoveries in the field of autonomic neuroscience to researchers, industry, policymakers, and the public worldwide. | D361: 1 | E361: Frontiers in Neuroscience | F361: =VLOOKUP(D361,分野ID!$A$2:$B$49,2,FALSE) -> Neuroscience
A362: 2067 | B362: Health Policy and Management | C362: The Health Policy and Management section is dedicated to publishing research on health systems policy and management of health service provider organisations. Led by Prof. Dr. Joris Van De Klundert from Adolfo Ibáñez University, the Health Policy and Management section welcomes submissions that advance theory, methodology, and empirical evidence in the healthcare policy and management domain with the objective to positively impact health services and outcomes as envisioned in SDG3; ensure healthy lives and promote well-being for all at all ages. Submissions in the following domains are particularly welcome: Submission to this section should be embedded in social health sciences and/or other scientific disciplines relevant for policy and management and use state of the art methods from these fields with a view towards advancing practice. We welcome studies at all health system levels, from international regulations to national and regional systems, to organizational (management) topics, to the delivery of specific services to subpopulations and personalized care. In alignment with WHO priorities and SDG 3 (Good Health and Wellbeing) and SDG 10 (Reducing Inequalities), we prioritize contributions regarding the policy and management of advancing universal health coverage to advance equitable, socially inclusive access to high quality health services. We especially welcome studies that address SDG3 policy and management priorities in areas such as maternal and child health, prevention and treatment of infectious diseases, and prevention and treatment of non-communicable diseases. We also welcome studies on the interaction between health policy and the various planetary boundaries in line with SDG 13 (Climate Action). While health policy and management are very broad disciplines by nature, the section has clear limits. To avoid overlap with other sections of our journal, studies related to their focus areas may be transferred. Moreover, studies that address health but not within the context of the health systems and health service provider organizations are typically out of scope. Studies that aren’t embedded in (social) policy and management sciences also are likely to be out of scope. Likewise, descriptive studies that report on current health system or services performances with limited contribution towards advancement of theory or practice may be considered out of scope. This multidisciplinary section is at the forefront of disseminating and communicating cutting-edge scientific knowledge and impactful discoveries in the field of health services to researchers, industry, policymakers, and the public worldwide. | D362: 2063 | E362: Frontiers in Health Services | F362: =VLOOKUP(D362,分野ID!$A$2:$B$49,2,FALSE) -> #N/A
A363: 3472 | B363: Discoveries | C363: The Discoveries section is dedicated to publishing research focused on novel observational reports on marine animals in their natural environment. Led by Dr. Austin Gallagher from Beneath the Waves, Inc., the Discoveries section welcomes submissions in various domains of marine science, which aim to enhance our understanding of marine species and their responses to human-induced changes. With the advent of rapidly improving technology, our ability to record the ocean and its species has expanded exponentially. Observations of rare or first-ever behaviors and unique phenomena are key for understanding the fundamental role of species and how they may respond to human-induced change. These records may create or expand baseline information on species biology and ecology, as well as their distributions, augment conservation assessments for threatened species, or provide new information for managers tasked with mitigating or reducing the effects of human activities on specific species. Additionally, they help provide context to findings from more expansive ecological or behavioral studies and experimental approaches. Given that these records often include striking photo and video assets of marine species, these papers will also foster inspiration and hope for the ocean amongst broader audiences. The aim of Discoveries is to create an accessible and exciting forum for publishing and disseminating reports from the ocean that provide new records of behavior, the description of unique or rare natural phenomena, new distributions of species, and eye-opening information on how species respond and adapt to changes in their environment. This specialty section recognizes, and supports, the notion that these reports should be short and direct, often relying on limited data obtained via observation or opportunistic methods. An additional goal of this section is to further democratize the process of scientific publishing and expand opportunities for exciting marine discoveries to enter the peer-reviewed literature, by welcoming contributions from wildlife experts, naturalists, tour operators, filmmakers, and ocean educators. Topics considered in the scope of this section include: Contributions to the section should focus only on marine animals: invertebrates, fishes, reptiles, birds, and mammals. Submissions must present data achieved through first-hand observation, or the analysis of empirically collected scientific data. In all cases, records must be obtained from field-based methods and approaches, and they must be collected by those listed as authors. The most common article type should be a Data Report. The section will not consider submissions from zoos, aquaria, nor domesticated animals. | D363: 655 | E363: Frontiers in Marine Science | F363: =VLOOKUP(D363,分野ID!$A$2:$B$49,2,FALSE) -> Marine Science
A364: 2038 | B364: Diagnostic and Forensic Neuropathology | C364: The Diagnostic and Forensic Neuropathology section focuses on advancing the understanding of human neuropathology in clinical, diagnostic, and forensic contexts. Under the leadership of Dr. Safa Al-Sarraj from King's College Hospital NHS Foundation Trust, the Diagnostic and Forensic Neuropathology section encourages submissions that explore the various aspects of neuropathology, aiming to enhance knowledge and facilitate the exchange of ideas and experiences in the field. Topics considered within the scope of this section include: Submissions to this section should provide comprehensive and in-depth knowledge about the diagnosis, treatment, and understanding of neuropathological conditions and their underlying mechanisms. In particular, the section welcomes submissions which support and advance the understanding of neuropathology, clinico-pathological correlations of neurological disorders, pathology of brain tumors and their genetics, pathology of demyelination, pathology of epilepsy and related disorders, pathology of neurodegeneration and dementia, pathology of neuroinflammation, pathology of neuromuscular diseases, and forensic neuropathology, including pathology of traumatic brain injury, in alignment with SDG 3 (Good Health and Well-being). This multidisciplinary section is at the forefront of disseminating and communicating cutting-edge scientific knowledge and impactful discoveries in the field of Diagnostic and Forensic Neuropathology to researchers, industry, policymakers, and the public worldwide. | D364: 141 | E364: Frontiers in Neurology | F364: =VLOOKUP(D364,分野ID!$A$2:$B$49,2,FALSE) -> Neurology
A365: 1075 | B365: Mathematical Finance | C365: The Mathematical Finance section is dedicated to publishing research focused on the application of mathematical and statistical methods in the financial market. Led by Dr. Young Shin Kim from Stony Brook University, the Mathematical Finance section welcomes submissions in the various domains of mathematical finance, which connect advanced mathematical theories with practical applications in finance. Topics considered in the scope of this section include: Submissions should provide detailed, in-depth knowledge about the application of mathematical and statistical methods to solve complex issues in finance. The section welcomes submissions which support and advance the SDG: 8 (Decent Work and Economic Growth) and 9 (Industry, Innovation and Infrastructure). The Mathematical Finance section does not consider submissions that lack a strong mathematical foundation or focus on unrelated fields. However, it is important to note that some interdisciplinary studies, such as those involving engineering or social sciences, may still be relevant if they contribute significantly to the understanding or development of mathematical finance theories and applications. As such, exclusions should be limited to articles that do not have a clear connection to mathematical finance or do not provide in-depth knowledge about the application of mathematical and statistical methods to solve complex issues in finance. This multidisciplinary section is at the forefront of disseminating and communicating cutting-edge scientific knowledge and impactful discoveries in the field of mathematical finance to researchers, industry, policymakers, and the public worldwide. | D365: 981 | E365: Frontiers in Applied Mathematics and Statistics | F365: =VLOOKUP(D365,分野ID!$A$2:$B$49,2,FALSE) -> Applied Mathematics and Statistics
A366: 74 | B366: Schizophrenia | C366: The Schizophrenia section is dedicated to publishing research focused on understanding the neurobiological basis of schizophrenia. Led by Dr. Ingrid Melle from the University of Oslo, the Schizophrenia section welcomes submissions in the various domains of psychiatry, which aim to connect the cellular and molecular aspects of the disorder with its clinical manifestations. Topics considered in the scope of this section include: Submissions should provide detailed, in-depth knowledge about the interplay between genetic and environmental factors in schizophrenia, as well as the underlying endophenotype and its impact on cognition and emotion. The section welcomes submissions which support and advance the SDG: SDG 3: Good Health and Well-being. The Schizophrenia section does not consider submissions focusing on general physical health, perinatal care, addiction, or aggression, unless they have a relevance to schizophrenia research, its etiology, or treatment. Additionally, studies on online services will only be considered if they are directly related to schizophrenia research or its management. Studies without a relevance to schizophrenia will be deemed outside the scope of this section. This multidisciplinary section is at the forefront of disseminating and communicating cutting-edge scientific knowledge and impactful discoveries in the field of psychiatry to researchers, industry, policymakers, and the public worldwide. | D366: 71 | E366: Frontiers in Psychiatry | F366: =VLOOKUP(D366,分野ID!$A$2:$B$49,2,FALSE) -> Psychiatry
A367: 1620 | B367: Neurotoxicology | C367: The Neurotoxicology section is dedicated to publishing research focused on understanding the adverse effects of chemical, biological, or physical elements on the nervous system with a focus on their relevance to human health. Led by Dr. Ellen Fritsche from the Swiss Centre for Applied Human Toxicology (SCAHT) and Dr. Helena Hogberg from the National Institute of Environmental Health Sciences (NIH). The Neurotoxicology section welcomes submissions in various domains of neurotoxicology, which aim to enhance our understanding of the nervous system's vulnerability, function, and responses to environmental or medical exposure. Topics considered in the scope of this section include: Submissions should provide detailed, in-depth knowledge about the mechanisms, assessment, and management of neurotoxicity and its impact on human health. In particular, the section welcomes submissions which support and advance the understanding of neurotoxicity, assessment, and management of its impact on human health, and contribute to SDGs 3 (Good Health and Well-being). The Neurotoxicology section does not consider the publication of data without human translation or relevance to toxic mechanisms, pathways, or outcomes. However, studies that provide valuable insights into the mechanisms, assessment, and management of neurotoxicity and its impact on human health, even if they do not have direct human translation, may still be considered for publication. Studies lacking a strong neurotoxicological component or those that do not contribute to the understanding of neurotoxicity, assessment, and management of its impact on human health will be deemed unsuitable for this section. This multidisciplinary section is at the forefront of disseminating and communicating cutting-edge scientific knowledge and impactful discoveries in the field of neurotoxicology to researchers, industry, policymakers, and the public worldwide. | D367: 473 | E367: Frontiers in Toxicology | F367: =VLOOKUP(D367,分野ID!$A$2:$B$49,2,FALSE) -> #N/A
A368: 531 | B368: Cytokines and Soluble Mediators in Immunity | C368: The Cytokines and Soluble Mediators in Immunity section is dedicated to publishing research focused on the role of soluble mediators in cell-to-cell communication and immune response regulation. Led by Dr. Silvano Sozzani from the Sapienza University of Rome, the Cytokines and Soluble Mediators in Immunity section welcomes submissions in the various domains of immunology, which explore the connections between soluble mediators and immune responses. Topics considered in the scope of this section include: Submissions should provide detailed, in-depth knowledge about the various aspects of soluble mediators and their impact on immune responses and regulation. The section welcomes submissions which support and advance the SDG: SDG 3 - Good Health and Well-being. The Cytokines and Soluble Mediators in Immunity section does not consider studies primarily focused on specific diseases or disorders, unless they have a foundation in the role of soluble mediators in immunity. This includes research on aortic valve stenosis, diabetes mellitus, macular degeneration, red blood cell disorders, or neurological disorders, which should only be submitted if they explore the connections between soluble mediators and immune responses. Bibliometric studies are outside of the scope of this section and may be rejected or redirected to other journals/sections as appropriate. This multidisciplinary section is at the forefront of disseminating and communicating cutting-edge scientific knowledge and impactful discoveries in the field of immunology to researchers, industry, policymakers, and the public worldwide. | D368: 276 | E368: Frontiers in Immunology | F368: =VLOOKUP(D368,分野ID!$A$2:$B$49,2,FALSE) -> Immunology
A369: 1896 | B369: Nanofabrication | C369: The Nanofabrication section is dedicated to publishing research focused on innovative techniques for creating reproducible patterns with elements sized 100 nm or less in at least one dimension. Led by Prof. John Fourkas from the University of Maryland, the Nanofabrication section welcomes submissions in various domains of nanotechnology, which connect the development of novel fabrication methods to their practical applications. Topics considered in the scope of this section include: Submissions should provide detailed, in-depth knowledge about the development and application of nanofabrication techniques. The section welcomes submissions that support and advance the SDG: SDG 9: Industry, Innovation and Infrastructure. Articles with a strong focus on device nanofabrication may be better suited to our sister Nanodevices section of the journal. Articles on synthesis of nanostructured and nanoscale materials are better suited for our sister Nanomaterials section of the journal. This multidisciplinary section is at the forefront of disseminating and communicating cutting-edge scientific knowledge and impactful discoveries in the field of nanotechnology to researchers, industry, policymakers, and the public worldwide. | D369: 1528 | E369: Frontiers in Nanotechnology | F369: =VLOOKUP(D369,分野ID!$A$2:$B$49,2,FALSE) -> #N/A
A370: 1742 | B370: Diabetes Self-Management | C370: The Diabetes Self-management section is devoted to publishing research centered on educational, and psychosocial aspects of diabetes management. Guided by Dr. Frank Snoek from the Amsterdam University Medical Center, the Diabetes Self-management section encourages submissions in various domains of clinical diabetes and healthcare, which aim to enhance the understanding of self-management processes and promote effective strategies for individuals affected by diabetes. Topics considered within the scope of this section include: Submissions should offer comprehensive, in-depth knowledge about strategies and interventions that help individuals living with diabetes achieve optimal physical and mental health outcomes. In particular, the section welcomes submissions using quantitative or qualitative methodologies, which support and advance the understanding of self-management processes, promotion of effective strategies for individuals affected by diabetes, and enhancement of clinical diabetes and healthcare, in alignment with SDG 3 (Good Health and Well-being). The Diabetes Self-Management section does not consider submissions that focus on purely methodological or technical research, general health topics, and non-diabetes-specific treatments. However, studies that are unrelated to improving self-management for individuals with diabetes but still contribute to the understanding of self-management processes, promotion of effective strategies for individuals affected by diabetes, and enhancement of clinical diabetes and healthcare will be considered. This multidisciplinary section is at the forefront of disseminating and communicating cutting-edge scientific knowledge and impactful discoveries in the field of Diabetes Self-Management to clinicians, researchers, industry, policymakers, and the public worldwide. | D370: 1729 | E370: Frontiers in Clinical Diabetes and Healthcare | F370: =VLOOKUP(D370,分野ID!$A$2:$B$49,2,FALSE) -> #N/A
A371: 2884 | B371: Osteoporosis | C371: The Osteoporosis section is dedicated to publishing research focused on innovative strategies for the diagnosis, prevention, and treatment of osteoporosis and related conditions. Led by Dr. Kenneth Saag from the University of Alabama at Birmingham, the Osteoporosis section welcomes submissions in the various domains of bone health, which connect interdisciplinary approaches to improve patient outcomes and enhance public health. Topics considered in the scope of this section include: Submissions should provide detailed, in-depth knowledge about the biology, diagnosis, prevention, and treatment of osteoporosis and metabolic bone diseases. In particular, the section welcomes submissions which support and advance the diagnosis, prevention, and treatment of osteoporosis and related conditions, and SDG 3: Good Health and Well-being. This multidisciplinary section is at the forefront of disseminating and communicating cutting-edge scientific knowledge and impactful discoveries in the field of bone health to researchers, industry, policymakers, and the public worldwide. | D371: 2882 | E371: Frontiers in Musculoskeletal Disorders | F371: =VLOOKUP(D371,分野ID!$A$2:$B$49,2,FALSE) -> #N/A
... A525: 832 | B525: Deep-Sea Environments and Ecology | C525: The Deep-Sea Environments and Ecology section is dedicated to publishing research focused on understanding the ecology of the deep sea, including aspects of the geological, geochemical, and oceanographic components that contribute to understand life in the deep sea, as well as the impacts of climate change and human activities on these ecosystems. Led by Dr. Ana Hilario from University of Aveiro, and Dr. Eva Ramirez-Llodra from REV Ocean, the Deep-Sea Environments and Ecology section welcomes submissions in the various domains of marine science, which connect interdisciplinary research to address the challenges faced by deep-sea ecosystems. Topics considered in the scope of this section include: Submissions should provide detailed, in-depth knowledge about the diverse aspects of deep-sea environments and ecology, focusing on the complex interactions between biological, geological, geochemical, oceanographic, and human factors. In particular, the section welcomes submissions which support and advance the deep-sea environments and ecology, focusing on ecosystem functioning, distribution, and connectivity; biodiversity, biological composition, and biogeography; geochemical-oceanographic-biological interactions; anthropogenic impacts, including climate-driven changes; and societal and economic challenges and governance (SDGs 13, 14, and 15). The Deep-Sea Environments and Ecology section does not consider studies that focus solely on shallow water ecosystems or research that emphasizes non-deep-sea specific aspects without a relevance to deep-sea environments and ecology. However, species distribution modeling and imaging techniques may be considered if they have a clear and direct relevance to deep-sea environments and ecology, as well as the complex interactions between geological, biological, and human factors. Similarly, this section does not consider studies where the focus is on abiotic data and processes, as these manuscripts should be directed to specialised journals in geology, geochemistry or physical oceanography. This multidisciplinary section is at the forefront of disseminating and communicating cutting-edge scientific knowledge and impactful discoveries in the field of marine science to researchers, industry, policymakers, and the public worldwide. | D525: 655 | E525: Frontiers in Marine Science | F525: =VLOOKUP(D525,分野ID!$A$2:$B$49,2,FALSE) -> Marine Science
A526: 1595 | B526: Motor Neuroscience | D526: 1588 | E526: Frontiers in Human Neuroscience | F526: =VLOOKUP(D526,分野ID!$A$2:$B$49,2,FALSE) -> Human Neuroscience
A527: 684 | B527: Pediatric Urology | C527: The Pediatric Urology section is dedicated to publishing research focused on advancing knowledge in pediatric urological conditions and treatments. Led by Dr. Miguel Castellan from the University of Miami, the Pediatric Urology section welcomes submissions in the various domains of pediatric urology, which connect fundamental research with clinical applications and outcomes. Topics considered in the scope of this section include: Submissions should provide detailed, in-depth knowledge about the various aspects of pediatric urology, aiming to present cutting-edge advances in the specialty, stimulate new research in all areas of genitourinary diseases of childhood, and promote discussion on the numerous controversial areas of the field. In particular, the section welcomes submissions which support and advance the pediatric urology, bladder dysfunction, genital reconstruction, improvements to existing techniques, long term outcomes, new diagnostic options, new surgical techniques and treatment modalities, pediatric genitourinary oncology, pediatric genitourinary systems, pediatric genitourinary trauma, pediatric renal transplantation, pediatric urolithiasis, prenatal diagnosis and treatment, prospective uni- or multi-institutional studies, ureteral obstruction, urethral obstruction, and urinary tract infections in support of SDG 3 (Good Health and Well-being). The Pediatric Urology section does not consider submissions focused on gene expression or network analysis, unless they have a foundation in pediatric urological conditions or treatments. Additionally, pain management studies are excluded unless they are directly related to pediatric urological issues. Studies that do not specifically address urological issues in the pediatric population are outside the scope of this section. This multidisciplinary section is at the forefront of disseminating and communicating cutting-edge scientific knowledge and impactful discoveries in the field of pediatric urology to researchers, industry, policymakers, and the public worldwide. | D527: 606 | E527: Frontiers in Pediatrics | F527: =VLOOKUP(D527,分野ID!$A$2:$B$49,2,FALSE) -> Pediatrics
A528: 3356 | B528: Energy Efficiency Materials | C528: The Energy Efficiency Materials section is dedicated to publishing research focused on the development and application of materials that enhance energy efficiency and conservation. Led by Prof. Davide Astiaso Garcia from Sapienza University of Rome, the Energy Efficiency Materials section welcomes submissions in various domains of energy efficiency materials, which aim to address the challenges of reducing energy demand, integrating renewable energy sources, and minimizing environmental impacts. Topics considered in the scope of this section include: Submissions should provide detailed, in-depth knowledge about the development, implementation, and impact of energy efficiency materials in various applications and industries. In particular, the section welcomes submissions which support and advance the energy efficiency materials, energy conservation, renewable energy sources, and environmental impact reduction (SDGs 7, 9, 11, 12, and 13). This multidisciplinary section is at the forefront of disseminating and communicating cutting-edge scientific knowledge and impactful discoveries in the field of energy efficiency materials to researchers, industry, policymakers, and the public worldwide. | D528: 3115 | E528: Frontiers in Energy Efficiency | F528: =VLOOKUP(D528,分野ID!$A$2:$B$49,2,FALSE) -> #N/A
A529: 711 | B529: Behavioral and Evolutionary Ecology | C529: The Behavioral and Evolutionary Ecology section is dedicated to publishing research focused on organismal biology and interactions between organisms and their environment. Led by Dr. Sasha Dall from the University of Exeter, the Behavioral and Evolutionary Ecology section welcomes submissions in the various domains of organismal biology, which connect the study of interactions between organisms and their biotic and abiotic environment. Topics considered in the scope of this section include: Submissions should provide detailed, in-depth knowledge about the interactions between organisms and their environment, as well as the evolutionary and ecological processes that shape these interactions. In particular, the section welcomes submissions which support and advance the understanding of organismal biology, interactions between organisms and their environment, and ecological processes, in relation to SDGs 13 (Climate Action), 14 (Life Below Water), and 15 (Life on Land). The Behavioral and Evolutionary Ecology section does not consider studies focusing solely on population level, community and ecosystem dynamics, social evolution, or medical treatment unless directly related to the behavior and evolution of organisms within their ecological context. Additionally, submissions that do not emphasize the interplay between behavior, evolution, and ecology are outside the scope of this section. However, the section does welcome submissions related to climate change, human impact, and other topics that support and advance the understanding of organismal biology, interactions between organisms and their environment, and ecological processes in relation to global sustainability goals. Authors should mention, in the methods or acknowledgements, any Field Stations or Marine Laboratories (FSMLs) where the research was conducted or that supported the research (e.g., assisted with permitting, facilitated land or data access, provided housing accommodations or research space, granted funding, etc.). This also includes others places of scientific infrastructure (e.g., botanical gardens, national laboratories, museums). Please include the FSML’s Research Organization Registry (ROR) number if available. This multidisciplinary section is at the forefront of disseminating and communicating cutting-edge scientific knowledge and impactful discoveries in the field of organismal biology to researchers, industry, policymakers, and the public worldwide. | D529: 471 | E529: Frontiers in Ecology and Evolution | F529: =VLOOKUP(D529,分野ID!$A$2:$B$49,2,FALSE) -> Ecology and Evolution
A530: 2860 | B530: Soft Coatings | C530: The Soft Coatings section is dedicated to publishing research focused on the advancement and applications of soft coatings in various industries. Led by Professor Vasileios Koutsos from the University of Edinburgh, the Soft Coatings section welcomes submissions in the various domains of coatings, dyes, and interface engineering, which address the challenges and opportunities in improving function, manufacturing, and life cycles/biocompatibility. Topics considered in the scope of this section include: Submissions should provide detailed, in-depth knowledge about the development, application, and improvement of soft coatings in various industries. In particular, the section welcomes submissions which support and advance the development, application, and improvement of soft coatings in various industries, contributing to SDGs 9 (Industry, Innovation, and Infrastructure), 12 (Responsible Consumption and Production), and 13 (Climate Action). This multidisciplinary section is at the forefront of disseminating and communicating cutting-edge scientific knowledge and impactful discoveries in the field of coatings to researchers, industry, policymakers, and the public worldwide. | D530: 2857 | E530: Frontiers in Coatings, Dyes and Interface Engineering | F530: =VLOOKUP(D530,分野ID!$A$2:$B$49,2,FALSE) -> #N/A
A531: 1562 | B531: Augmented Reality | C531: The Augmented Reality section is dedicated to publishing research focused on the technology and foundations of augmented reality. Led by Dr. Mark Billinghurst from the University of South Australia, the Augmented Reality section welcomes submissions in the various domains of augmented reality, which connect the real and virtual worlds to enhance human perception and interaction. Topics considered in the scope of this section include: Submissions should provide detailed, in-depth knowledge about the integration of real and virtual content, interaction devices, and tracking technology in augmented reality systems. The section welcomes submissions which support and advance the SDG: SDG 9: Industry, Innovation and Infrastructure. The Augmented Reality section does not consider submissions that primarily focus on object recognition or object-oriented programming without a fundamental basis in the development, enhancement, or application of augmented reality systems and experiences. This multidisciplinary section is at the forefront of disseminating and communicating cutting-edge scientific knowledge and impactful discoveries in the field of augmented reality to researchers, industry, policymakers, and the public worldwide. | D531: 1561 | E531: Frontiers in Virtual Reality | F531: =VLOOKUP(D531,分野ID!$A$2:$B$49,2,FALSE) -> Virtual Reality
A532: 673 | B532: Condensed Matter Physics | C532: The Condensed Matter Physics section is dedicated to publishing research focused on the fundamental and applied aspects of condensed matter and materials physics. Led by Dr. James Sauls from Louisiana State University and Dr. Matthias Eschrig from the University of Greifswald, the Condensed Matter Physics section welcomes submissions in various domains of condensed matter physics, which connect theoretical, experimental, and practical aspects of the field. Topics considered in the scope of this section include: Submissions should provide detailed, in-depth knowledge about the various aspects of condensed matter physics, covering a wide range of topics and phenomena. The Condensed Matter Physics section does not consider submissions that are unrelated to the fundamental properties and behavior of condensed matter systems. Studies that primarily focus on biological, chemical, or engineering aspects without a strong connection to condensed matter physics are excluded. However, research that supports and advances the goal of industry, innovation, and infrastructure, while maintaining a clear theoretical or experimental basis in condensed matter physics, is considered within the scope of this section. This multidisciplinary section is at the forefront of disseminating and communicating cutting-edge scientific knowledge and impactful discoveries in the field of condensed matter physics to researchers, industry, policymakers, and the public worldwide. | D532: 616 | E532: Frontiers in Physics | F532: =VLOOKUP(D532,分野ID!$A$2:$B$49,2,FALSE) -> Physics
A533: 2902 | B533: Case Management | C533: The Case Management section is dedicated to publishing research focused on the management of malaria infections. Led by Dr. Ghyslain Mombo-Ngoma at Centre de Recherche Médicales de Lambaréné Lambaréné, Gabon, the Case Management section welcomes submissions in the various domains of malaria management, which contribute to the global efforts to control and eliminate the disease. Topics considered in the scope of this section include: Submissions should provide detailed, in-depth knowledge about improving the diagnosis, treatment, and preventive treatment of malaria. In particular, the section welcomes submissions which support and advance the management of malaria infections, antimalarial medicines quality, clinical development of novel antimalarial drugs, and prevention strategies, contributing to SDG 3 (Good Health and Well-being). This multidisciplinary section is at the forefront of disseminating and communicating cutting-edge scientific knowledge and impactful discoveries in the field of malaria management to researchers, industry, policymakers, and the public worldwide. | D533: 2896 | E533: Frontiers in Malaria | F533: =VLOOKUP(D533,分野ID!$A$2:$B$49,2,FALSE) -> #N/A
A534: 2412 | B534: Optoelectronic and Photonic Sensors | C534: The Optoelectronic and Photonic Sensors section is committed to publishing research centered on advancing sensing technologies using electro-optic and photonic means. Under the guidance of Prof. Kyunghwan Oh from Yonsei University, the Optoelectronic and Photonic Sensors section encourages submissions that explore various aspects of optoelectronic and photonic sensing. These include sensor design and structure, multi-modal sensing capability, in-situ real-time monitoring technologies, and their applications in emerging areas such as energy storage systems, autonomously manoeuvring vehicles, IoT-driven smart manufacturing systems, biochemical monitoring, and high precision quantum measurements. Topics considered within the scope of this section include: Submissions should offer comprehensive knowledge about innovative optoelectronic and photonic sensing technologies and their applications. Reports dealing with mechanical reliability do not fall within the scope of this section and should be submitted to more specialized journals. Aspects relating to photon generation, reception and conversion are not restricted to fundamental work, therefore, this section operates in close collaboration with our sister Journal, Frontiers in Photonics. The section welcomes submissions which support the Sustainable Development Goals, and in particular SDGs 3 (Good Health and Well-being), SDG 7 (Affordable and Clean Energy) and SDG 9 (Industry, Innovation, and Infrastructure). This multidisciplinary section is at the forefront of disseminating and communicating cutting-edge scientific knowledge and impactful discoveries in the field of Optoelectronic and Photonic Sensors to researchers, industry, policymakers, and the public worldwide. | D534: 1704 | E534: Frontiers in Sensors | F534: =VLOOKUP(D534,分野ID!$A$2:$B$49,2,FALSE) -> #N/A
A535: 1910 | B535: Blockchain Economics | C535: The Blockchain Economics section is dedicated to publishing research focused on the exploration of socio-economic systems transitioning towards open models built on distributed ledger technologies and blockchain. Led by Dr. Claudio Tessone from the University of Zurich and Dr. Paolo Tasca from University College London Centre for Blockchain Technologies, the Blockchain Economics section welcomes submissions in various domains of blockchain and economics, which address fundamental questions and bridge the gap between technology and economic theory. Topics considered in the scope of this section include: Submissions should provide detailed, in-depth knowledge about the various aspects of blockchain economics, including theoretical and empirical studies that advance the state of the art in this area. The section welcomes submissions which support and advance the SDG: SDG 8: Decent Work and Economic Growth, SDG 9: Industry, Innovation, and Infrastructure, SDG 10: Reduced Inequalities, SDG 16: Peace, Justice, and Strong Institutions, and SDG 17: Partnerships for the Goals. This multidisciplinary section is at the forefront of disseminating and communicating cutting-edge scientific knowledge and impactful discoveries in the field of blockchain and economics to researchers, industry, policymakers, and the public worldwide. | D535: 1418 | E535: Frontiers in Blockchain | F535: =VLOOKUP(D535,分野ID!$A$2:$B$49,2,FALSE) -> #N/A
A536: 1872 | B536: Security, Privacy and Authentication | C536: The Security, Privacy, and Authentication section is dedicated to publishing research focused on the protection and verification of communication, network, and Internet of Things (IoT) systems. Led by Dr. Charith Perera from Cardiff University, the Security, Privacy, and Authentication section welcomes submissions in the various domains of IoT security, privacy, and authentication, which connect the scientific and research community with industry professionals and practitioners. Topics considered in the scope of this section include: Submissions should provide detailed, in-depth knowledge about the security, privacy, and authentication aspects of IoT communications and network systems. Submissions in all formats/styles including original research, perspective/vision papers, tutorials/surveys (review), magazines (mini review), letters (brief research report), as well as replies and comments are encouraged. However, any papers relating to these subjects in the context of computing systems will not be considered and will be transferred to other journals. The section welcomes submissions which support and advance the following SDGs: SDG 9: Industry, Innovation and Infrastructure , SDG 11 Make cities and human settlements inclusive, safe, resilient and sustainable, SDG 16 Promote peaceful and inclusive societies for sustainable development, provide access to justice for all and build effective, accountable and inclusive institutions at all levels, and SDG 17 Strengthen the means of implementation and revitalize the Global Partnership for Sustainable Development. This multidisciplinary section is at the forefront of disseminating and communicating cutting-edge scientific knowledge and impactful discoveries in the field of IoT security to researchers, industry, policymakers, and the public worldwide. | D536: 1787 | E536: Frontiers in Communications and Networks | F536: =VLOOKUP(D536,分野ID!$A$2:$B$49,2,FALSE) -> #N/A
A537: 3652 | B537: Human Bioarchaeology and Paleopathology | C537: The Human Bioarchaeology and Paleopathology section is dedicated to publishing research focused on understanding the human condition as it resides at the intersection of past environments, biology, and culture. Led by Dr. Pamela L. Geller from the University of Miami, the Human Bioarchaeology and Paleopathology section welcomes submissions in the various domains of bioarchaeology, osteoarchaeology, and paleopathology, which contribute to a deeper understanding of human biology, health, activities, and behaviour. Topics considered in the scope of this section advance theorizing, methodological innovation, and consolidation of a bioethos: The section welcomes submissions which support and advance the SDGs (e.g. SDG 3: Good Health and Well-being, SDG 4: Quality Education, SDG 11: Sustainable Cities and Communities, and SDG 15: Life on Land). This multidisciplinary section is at the forefront of disseminating and communicating cutting-edge scientific knowledge and impactful discoveries in the field of bioarchaeology to researchers, industry, policymakers, and the public worldwide. | D537: 2756 | E537: Frontiers in Environmental Archaeology | F537: =VLOOKUP(D537,分野ID!$A$2:$B$49,2,FALSE) -> #N/A
A538: 2325 | B538: Natural Product Biosynthesis | C538: The Natural Product Biosynthesis section is dedicated to publishing research focused on the exploration and understanding of natural product biosynthesis processes. Led by Dr. Olga Genilloud from Fundación MEDINA, the Natural Product Biosynthesis section welcomes submissions in the various domains of natural product biosynthesis, which connect fundamental and applied research to advance the knowledge in this field. Topics considered in the scope of this section include: Submissions should provide detailed, in-depth knowledge about the biosynthesis of natural products and their underlying mechanisms. The section welcomes submissions which support and advance the SDG 9: Industry, Innovation and Infrastructure, SDG 12: Responsible Consumption and Production, SDG 13: Climate Action, and SDG 15: Life on Land. This multidisciplinary section is at the forefront of disseminating and communicating cutting-edge scientific knowledge and impactful discoveries in the field of natural product biosynthesis to researchers, industry, policymakers, and the public worldwide. | D538: 2320 | E538: Frontiers in Natural Products | F538: =VLOOKUP(D538,分野ID!$A$2:$B$49,2,FALSE) -> #N/A
... A544: 2218 | B544: Glycoscience | C544: The Glycoscience section is dedicated to publishing research focused on the study of glycans and glycoconjugates in living organisms and their interactions with proteins. Led by Dr. Matthew DeLisa from Cornell University, the Glycoscience section welcomes submissions in the various domains of glycoscience, which connect the fields of biology, chemistry, medicine, and engineering to provide a comprehensive understanding of the subject. Topics considered in the scope of this section include: Submissions should provide detailed, in-depth knowledge about the biosynthesis, biology, structure, and evolution of glycans and glycoconjugates, as well as the proteins that recognize them. The section welcomes submissions which support and advance the SDG: SDG 3: Good Health and Well-being, SDG7: Affordable and Clean Energy, SDG 9: Industry, Innovation, and Infrastructure, SDG 12: Responsible Consumption and Production, SDG 15: Life on Earth, and SDG 17: Partnerships for the Goals. The Glycoscience section does not consider submissions that do not have a foundation in glycoscience or the study of carbohydrates and their derivatives. For example, studies focused on cancer research, tumor biology, or treatment methods are not in scope. However, studies related to glyco-oncology, which explore the role of glycans and glycoconjugates in cancer development and treatment, are within the scope of this section. Additionally, submissions without a clear emphasis on glycosylation or glycan-related processes are outside the scope of this section. This multidisciplinary section is at the forefront of disseminating and communicating cutting-edge scientific knowledge and impactful discoveries in the field of glycoscience to researchers, industry, policymakers, and the public worldwide. | D544: 698 | E544: Frontiers in Molecular Biosciences | F544: =VLOOKUP(D544,分野ID!$A$2:$B$49,2,FALSE) -> Molecular Biosciences
A545: 1337 | B545: Mathematics and Economics | D545: 979 | E545: Frontiers for Young Minds | F545: =VLOOKUP(D545,分野ID!$A$2:$B$49,2,FALSE) -> #N/A
A546: 3503 | B546: Medical Diagnostics | C546: The Medical Diagnostics section is dedicated to publishing research focused on advancing human and animal health through lab-on-a-chip technologies for clinical diagnostics. Led by Prof. Tony Cass from Imperial College London, the Medical Diagnostics section welcomes submissions in the applications of lab-on-a-chip technologies, which aim to enhance diagnostic capabilities and reduce costs and time to result whilst delivering analytical performance comparable to that achieved by conventional approaches in centralized laboratories. Topics considered in the scope of this section include: Submissions should provide detailed, in-depth knowledge about innovative approaches to medical diagnostics, including sample preparation, analyte separation, and detection, using lab-on-a-chip technologies. Submissions that validate lab-on-a-chip technologies and comparison with ‘gold standard’ methods are also welcome. In particular, the section particularly welcomes submissions which support Sustainable Development Goals 3 (Good Health and Well-being) and 9 (Industry, Innovation, and Infrastructure). Studies that describe routine applications of well-established technologies (for example immunoassays) are out of the scope for this section. This multidisciplinary section is at the forefront of disseminating and communicating cutting-edge scientific knowledge and impactful discoveries in the field of lab-on-a-chip technologies to researchers, healthcare professionals, industry, policymakers, and the public worldwide. | D546: 2670 | E546: Frontiers in Lab on a Chip Technologies | F546: =VLOOKUP(D546,分野ID!$A$2:$B$49,2,FALSE) -> #N/A
A547: 3461 | B547: Thermal Energy Storage and Conversion | C547: The Thermal Energy Storage and Conversion (TESC) section is dedicated to publishing research focused on advancing and understanding fundamental and applied research on all heat and mass transfer modes involving and applied to TESC technologies. Led by Dr. Bidyut Saha from Kyushu University, the section welcomes submissions of new knowledge, progress, and technological advancements related to thermal energy storage and conversion. These contributions have the potential to aid the development of sustainable energy solutions by reducing reliance on fossil fuels. Topics considered in the scope of this section include: Submissions should provide detailed, in-depth knowledge about the various aspects of thermal energy conversion and storage technologies. Submissions should provide detailed, in-depth knowledge about these technologies' various aspects. The section specifically welcomes research that aligns with Sustainable Development Goals (SDG): Affordable and Clean Energy (SDG 7), Industry, Innovation, and Infrastructure (SDG 9), and Climate Action (SDG 13). This multidisciplinary section is at the forefront of disseminating and communicating cutting-edge scientific knowledge and impactful discoveries in the field of thermal engineering to researchers, industry, policymakers, and the public worldwide. | D547: 2105 | E547: Frontiers in Thermal Engineering | F547: =VLOOKUP(D547,分野ID!$A$2:$B$49,2,FALSE) -> #N/A
A548: 215 | B548: Exercise Physiology | C548: The Exercise Physiology section is dedicated to publishing research focused on understanding the physiological mechanisms underlying exercise and its effects on humans and animals. Led by Dr. Giuseppe D'Antona from the Interdepartmental Center in Motor and Sports Activities, Sport Medicine Centre, University of Pavia, the Exercise Physiology section welcomes submissions in various domains of exercise physiology, which aim to elucidate the connections between molecular, cellular, and systemic responses to exercise. Topics considered in the scope of this section include: Submissions should provide detailed, in-depth knowledge about the physiological mechanisms and responses related to exercise, encompassing molecular, cellular, and systemic levels. The section welcomes submissions which support and advance the SDG: SDG 3: Good Health and Well-being. The Exercise Physiology section does not consider descriptive and sports-related studies that do not primarily focus on the physiological mechanisms behind exercise. In addition, studies reporting medical imaging, gene expression, or dealing with pathologies, are considered unsuitable for this section, unless they have a strong foundation in the physiological adaptations to exercise or physical activity. Finally, case reports are welcome if physiological measurements are conducted. This multidisciplinary section is at the forefront of disseminating and communicating cutting-edge scientific knowledge and impactful discoveries in the field of exercise physiology to researchers, industry, policymakers, and the public worldwide. | D548: 210 | E548: Frontiers in Physiology | F548: =VLOOKUP(D548,分野ID!$A$2:$B$49,2,FALSE) -> Physiology
A549: 1873 | B549: Smart Grid Communications | C549: The Smart Grid Communications section is dedicated to publishing research focused on advancing communication technologies for smart grids. Led by Dr. Melike Erol-Kantarci from the University of Ottawa, the Smart Grid Communications section welcomes submissions in various domains of smart grid communications, which contribute to the enhancement of communication systems and protocols for efficient energy management. Topics considered in the scope of this section include: Submissions should provide detailed, in-depth knowledge about the development and implementation of communication technologies for smart grids. In particular, the section welcomes submissions which support and advance the smart grid communications, capacity and network planning, resource and service discovery, coexistence, convergence, and interoperability mechanisms, communication protocols optimized for information collection and control applications, fifth-generation and machine-type communications, machine learning-based smart grid communications, multi-hop communication and mesh networking, physical and MAC layer protocols for smart grid communications, power line communications, scalable network and system architecture for smart grids, self-healing and adaptive communication protocols and algorithms, and SDGs 7 (Affordable and Clean Energy), 9 (Industry, Innovation and Infrastructure), and 13 (Climate Action). This multidisciplinary section is at the forefront of disseminating and communicating cutting-edge scientific knowledge and impactful discoveries in the field of smart grid communications to researchers, industry, policymakers, and the public worldwide. | D549: 1787 | E549: Frontiers in Communications and Networks | F549: =VLOOKUP(D549,分野ID!$A$2:$B$49,2,FALSE) -> #N/A
A550: 3006 | B550: Social and Emotional Development | C550: The Social and Emotional Development section is dedicated to publishing research focused on the growth and enhancement of social and emotional competencies in individuals across various life stages. The Social and Emotional Development section welcomes submissions in the various domains of developmental psychology, which aim to advance the understanding of social and emotional development and its impact on human well-being. Topics considered in the scope of this section include: Submissions should provide detailed, in-depth knowledge about the factors influencing social and emotional development and their implications for individuals and society. In particular, the section welcomes submissions which support and advance the social and emotional development, diversity, emotional understanding, expression, and regulation, interventions, policy, social and emotional experiences in context, social behaviors, social cognitions, social interactions and relationships, and social emotional learning (SDG 3: Good Health and Well-being, SDG 4: Quality Education, and SDG 10: Reduced Inequalities). The Social and Emotional Development section does not consider studies primarily focused on other aspects of developmental psychology, cognitive development, lifespan development, infancy, or adolescence without a clear connection to social or emotional development. Additionally, research centered on clinical treatment, neuroscientific investigations without a clear social or emotional component, or studies on physical development or motor skills are considered outside the scope of this section. Submissions should have a primary focus on social-emotional development and not be limited to other domains of psychology or other fields. All studies must contribute insights into social or emotional development. Studies that examine antecedents, correlates, or consequences of social and emotional functioning will be included, provided the primary focus of the study is on social or emotional factors. Studies that primarily focus on other aspects of developmental psychology and those that focus primarily on other domains of psychology or other fields should be submitted to specialized journals in the appropriate area, and studies that primarily focus on other aspects of developmental psychology should be submitted to the other appropriate sections of this journal. Specifically, studies that are primarily focused on aspects of cognitive development should go to the Cognitive Development section of Frontiers in Developmental Psychology. Studies that are limited to the periods of Infancy or Adolescence might consider submitting to other sections in the journal, but could also be submitted here; studies that span two developmental periods and focus primarily on social-emotional development are a good fit for this section. Those studies that focus primarily on other domains of psychology (clinical psychology, neuropsychology, etc) or other fields should be submitted to Frontiers in Psychology or other specialized journals in the appropriate area. This multidisciplinary section is at the forefront of disseminating and communicating cutting-edge scientific knowledge and impactful discoveries in the field of developmental psychology to researchers, industry, policymakers, and the public worldwide. | D550: 2999 | E550: Frontiers in Developmental Psychology | F550: =VLOOKUP(D550,分野ID!$A$2:$B$49,2,FALSE) -> #N/A
A551: 1911 | B551: Human-Wildlife Interactions | C551: The Human-Wildlife Interactions section is dedicated to publishing research focused on exploring the complex relationships between humans and wildlife. Led by Dr. Alexandra Zimmermann from the University of Oxford, the Human-Wildlife Interactions section welcomes submissions in the various domains of conservation science, which aim to address critical questions and provide insights for policy and practice in the field. Topics considered in the scope of this section include: Submissions should provide detailed, in-depth knowledge about the interactions between humans and wildlife, and their implications for conservation and sustainable development. All papers should ask and answer pressing questions in conservation and have relevance to the science, practice and/or policy related to human-wildlife dynamics. We welcome empirical, applied, and methodological contributions. Authors must highlight the conservation and management relevance of their studies in their submissions. More fundamental studies of ecology or evolution should be directed to our sister journal, Frontiers in Ecology and Evolution. Authors should mention, in the methods or acknowledgements, any Field Stations or Marine Laboratories (FSMLs) where the research was conducted or that supported the research (e.g., assisted with permitting, facilitated land or data access, provided housing accommodations or research space, granted funding, etc.). This also includes others places of scientific infrastructure (e.g., botanical gardens, national laboratories, museums). Please include the FSML’s Research Organization Registry (ROR) number if available. This multidisciplinary section is at the forefront of disseminating and communicating cutting-edge scientific knowledge and impactful discoveries in the field of conservation science to researchers, industry, policymakers, and the public worldwide. | D551: 1724 | E551: Frontiers in Conservation Science | F551: =VLOOKUP(D551,分野ID!$A$2:$B$49,2,FALSE) -> #N/A
A552: 2413 | B552: Gastrointestinal Cancers: Colorectal Cancer | C552: The Gastrointestinal Cancers: Colorectal Cancer section is dedicated to publishing research focused on advancing the understanding and treatment of colorectal neoplasia. Led by Dr. Yun Dai from First Hospital, Peking University, and Dr. Liang Qiao from Faculty of Medicine and Health, The University of Sydney, the Gastrointestinal Cancers: Colorectal Cancer section welcomes submissions in the various domains of colorectal cancer research, which aim to accelerate the clinical applications of biological advances. Topics considered in the scope of this section include: Submissions should provide detailed, in-depth knowledge about the various aspects of colorectal cancer research, from prevention and early detection to treatment and drug development. The section welcomes submissions which support and advance the SDG: SDG 3: Good Health and Well-being. The Gastrointestinal Cancers: Colorectal Cancer section does not consider manuscripts focusing on cancer risk factors and stratification, as well as in silico studies without cell line validation. However, the section welcomes meta-analyses and descriptive studies based on rigorous statistical methods or systematic reviews. Additionally, studies containing purely surgical procedures treating CRCs are excluded, unless they are directly related to the integrated treatments of advanced cancer or endoscopic identification and treatment of early neoplasia. Case reports that are not well-studied (e.g., without correlative data, diagnosis not convincingly established, no research components, etc). Submissions that are surgical in nature are also not in scope for this section. While we welcome meta-analyses and descriptive studies based on rigorous statistical methods or systematic reviews, case reports should include correlative data and expand the current knowledge on the pathophysiological and clinical manifestations of cancer. Manuscripts consisting solely of bioinformatics, computational analysis, or predictions of public databases without validation are not suitable for publication. Studies unrelated to colorectal cancer, its diagnosis, treatment, or prevention, as well as research focusing on other gastrointestinal cancers, non-cancerous gastrointestinal conditions, or general oncology without a specific connection to colorectal cancer are outside the scope of this section. This multidisciplinary section is at the forefront of disseminating and communicating cutting-edge scientific knowledge and impactful discoveries in the field of colorectal cancer research to researchers, industry, policymakers, and the public worldwide. | D552: 451 | E552: Frontiers in Oncology | F552: =VLOOKUP(D552,分野ID!$A$2:$B$49,2,FALSE) -> Oncology
A553: 91 | B553: Psychopharmacology | C553: The Psychopharmacology section is dedicated to publishing research focused on advancing the understanding and treatment of neuropsychiatric disorders. Led by Dr. Roberto Ciccocioppo from the University of Camerino, the Psychopharmacology section welcomes submissions in various domains of psychopharmacology, which aim to enhance the knowledge and development of novel treatments for central nervous system (CNS) disorders. Topics considered in the scope of this section include: Submissions should provide detailed, in-depth knowledge about the underlying mechanisms, potential treatments, and advancements in the field of psychopharmacology. The section welcomes submissions which support and advance the SDG: SDG 3: Good Health and Well-being. The Psychopharmacology section does not consider submissions focused on surgical procedures, inflammation, or cell biology, unless they have a fundamental basis in psychopharmacological mechanisms or interventions. Studies that do not emphasize the psychological or pharmacological aspects will be considered outside the scope of this section. However, submissions related to aging and dementia will be considered if they are relevant to the understanding and treatment of neuropsychiatric disorders and have a strong psychopharmacological component. This multidisciplinary section is at the forefront of disseminating and communicating cutting-edge scientific knowledge and impactful discoveries in the field of psychopharmacology to researchers, industry, policymakers, and the public worldwide. | D553: 71 | E553: Frontiers in Psychiatry | F553: =VLOOKUP(D553,分野ID!$A$2:$B$49,2,FALSE) -> Psychiatry
A554: 2903 | B554: Antimalarial Drug Resistance | C554: The Antimalarial Drug Resistance section is dedicated to publishing research focused on understanding and addressing drug resistance in malaria. Led by Dr. Mehul Dhorda from Mahidol Oxford Tropical Medicine Research Unit (MORU) and Dr. José Pedro Gil from Karolinska Institutet (KI), the Antimalarial Drug Resistance section welcomes submissions in various domains of antimalarial drug resistance research, which aim to enhance the development of effective treatments and public health strategies. Topics considered in the scope of this section include: Submissions should provide detailed, in-depth knowledge about the emergence and mechanisms of antimalarial drug resistance, as well as its potential impact on clinical practice and public health strategies. Relevant animal models and diverse research perspectives are also encouraged within the scope of this section. The section welcomes submissions which support and advance the SDG: SDG 3: Good Health and Well-being. This multidisciplinary section is at the forefront of disseminating and communicating cutting-edge scientific knowledge and impactful discoveries in the field of antimalarial drug resistance research to researchers, industry, policymakers, and the public worldwide. | D554: 2896 | E554: Frontiers in Malaria | F554: =VLOOKUP(D554,分野ID!$A$2:$B$49,2,FALSE) -> #N/A
A555: 672 | B555: Statistical and Computational Physics | C555: The Statistical and Computational Physics section is dedicated to publishing high-quality research that focuses on the study of systems with a large number of individual constituents or degrees of freedom, large-scale disorder, complex geometries, and random structures, as well as the computational methods required to address these systems. Led by Dr. José Andrade Jr. from the Federal University of Ceará and Dr. Marcel Filoche from the École Supérieure de Physique et de Chimie Industrielles de la Ville de Paris, this section welcomes submissions from various domains of physics that connect diverse research perspectives and tackle challenges in this field. Topics within the scope of this section include, but are not limited to: Submissions should provide in-depth insights and significantly advance the understanding of statistical and computational physics. The section prioritizes work that establishes strong connections to these fields, ensuring relevance and impact. Submissions primarily focused on unrelated disciplines, such as computer science or applied mathematics, without clear contributions to the core areas of statistical and computational physics, will not be considered. This multidisciplinary section is at the forefront of disseminating and communicating cutting-edge scientific knowledge and impactful discoveries in the field of physics to researchers, industry, policymakers, and the public worldwide. | D555: 616 | E555: Frontiers in Physics | F555: =VLOOKUP(D555,分野ID!$A$2:$B$49,2,FALSE) -> Physics
A556: 1563 | B556: Biomedical Nanotechnology | C556: The Biomedical Nanotechnology section is dedicated to publishing research focused on nano-enabled therapeutic and diagnostic approaches in healthcare and medicine. Led by Prof. Ajeet Kaushik from Florida Polytechnic University, the Biomedical Nanotechnology section welcomes submissions in various domains of biomedical nanotechnology, which connect physical and chemical technological advancements with high-impact biomedical applications. Topics considered in the scope of this section include: Submissions should provide detailed, in-depth knowledge about the development and application of nanotechnology in healthcare and medicine. In particular, the section welcomes submissions which support and advance the biomedical nanotechnology, micro- and nano-fluidics, micro- and nano-systems, micro- and nano-separation technologies, micro- and nano-total analysis systems, miniaturized medical diagnostics, miniaturized medical devices and treatment, drug development and delivery, single cell analysis, organ-on-a-chip, and bioinformatic and numerical aspects of nanotechnology for healthcare, in alignment with SDG 3 (Good Health and Well-being) and SDG 9 (Industry, Innovation, and Infrastructure). The Biomedical Nanotechnology section does not consider papers focusing on clinical and translational research, healthcare economics, or the general effects of technology on health without a strong emphasis on the application or development of nanotechnology in the biomedical field. Additionally, studies on antibacterial treatments are considered outside the scope if they do not have a nanotechnology component. This multidisciplinary section is at the forefront of disseminating and communicating cutting-edge scientific knowledge and impactful discoveries in the field of biomedical nanotechnology to researchers, industry, policymakers, and the public worldwide. | D556: 1528 | E556: Frontiers in Nanotechnology | F556: =VLOOKUP(D556,分野ID!$A$2:$B$49,2,FALSE) -> #N/A
A557: 2861 | B557: Dyes and Pigments | C557: The Dyes and Pigments section is dedicated to publishing research focused on the study and application of natural and synthetic coloring materials. Led by Dr. K. R. Justin Thomas from the Indian Institute of Technology Roorkee, the Dyes and Pigments section welcomes submissions in the various domains of color chemistry, which connect fundamental research with practical applications. Topics considered in the scope of this section include: Submissions should provide detailed, in-depth knowledge about the synthesis, characterization, and application of dyes and pigments in various fields, such as electronic devices, textiles, and other related areas. In particular, the section welcomes submissions which support and advance the study and application of natural and synthetic coloring materials, synthesis and characterization of dyes, and their applications in electronic devices such as organic light-emitting diodes, photovoltaics, etc., photodegradation of dyes, photochemistry of dyes, photodynamic therapy, application as photosensitizers or photocatalysts for organic transformations, textiles, and other related areas (SDG 9: Industry, Innovation and Infrastructure; SDG 12: Responsible Consumption and Production). This multidisciplinary section is at the forefront of disseminating and communicating cutting-edge scientific knowledge and impactful discoveries in the field of color chemistry to researchers, industry, policymakers, and the public worldwide. | D557: 2857 | E557: Frontiers in Coatings, Dyes and Interface Engineering | F557: =VLOOKUP(D557,分野ID!$A$2:$B$49,2,FALSE) -> #N/A
... A591: 760 | B591: Marine Evolutionary Biology, Biogeography and Species Diversity | C591: The Marine Evolutionary Biology, Biogeography and Species Diversity section is dedicated to publishing research focused on understanding the evolution, biogeography, and species diversity of marine life. Led by Dr. Jin Sun from Ocean University and Dr. Katrin Linse from British Antarctic Survey, the Marine Evolutionary Biology, Biogeography and Species Diversity section seeks to publish works on the evolution of life in the oceans over space and time, and on the species diversity of mainly eukaryotes. The marine realm is home to an outstanding biodiversity, yet the vast majority of this has yet to be discovered, described, and placed in an evolutionary context. Topics considered in the scope of this section include: Submissions should provide detailed, in-depth knowledge about the evolution, biogeography, and species diversity of marine organisms, with a particular emphasis on multidisciplinary, comparative, and multi-species approaches. In particular, the section welcomes submissions which support and advance the marine evolutionary biology, biogeography, and species diversity, and SDGs 14 (Life Below Water) and 15 (Life on Land). Taxonomic and systematic studies (incl. descriptions of new taxa) are welcome if they are of interest to the wide international readership, offer theoretical or methodological advances, focus on precisely framed evolutionary or biogeographical questions and/or address issues such as new habitats (such as deep-sea) or symbiosis. New taxon names or nomenclatural acts must be registered in ZOOBANK and have associated Life Science Identifiers (LSIDs). The Marine Evolutionary Biology, Biogeography and Species Diversity section does not consider studies on cetaceans, pinnipeds, sirenians, marine and estuarine reptiles, large fishes such as billfishes, tunas, sharks and rays and seabirds (should be submitted to Marine Megafauna). It also does not consider research on the evolutionary biology, biogeography and diversity of microbes and those papers should be submitted to the section Aquatic Microbiology. This section will consider genomic studies at a phylogenetic or multiple-species level, but work reporting on mitogenome, transcriptome or genome sequence analysis of a single species may benefit from submission to the section Marine Molecular Biology and Ecology. Note that species lists, biodiversity assessments without state-of-the art analyses, or the description of new taxa without an overarching evolutionary, ecological and/or biogeographical question will not be considered. | D591: 655 | E591: Frontiers in Marine Science | F591: =VLOOKUP(D591,分野ID!$A$2:$B$49,2,FALSE) -> Marine Science
A592: 3327 | B592: Engineering and Technology | D592: 979 | E592: Frontiers for Young Minds | F592: =VLOOKUP(D592,分野ID!$A$2:$B$49,2,FALSE) -> #N/A
A593: 2984 | B593: Antibiotic Resistance and New Antimicrobial drugs | C593: The Antibiotic Resistance and New Antimicrobial Drugs section is dedicated to publishing research focused on the study and development of antimicrobials and their interactions with various infectious agents. Led by Dr. Costas Papagiannitsis from the University of Thessaly, Dr. George Araj from the American University of Beirut, and Dr. Vincent Cattoir from the University of Rennes, the Antibiotic Resistance and New Antimicrobial Drugs section welcomes submissions in the various domains of cellular and infection microbiology, which connect the understanding of resistance mechanisms to the improvement of patient care and public health. Topics considered in the scope of this section include: Submissions should provide detailed, in-depth knowledge about the interactions between antimicrobials and infectious agents, as well as the development of new drugs and treatment strategies to combat antibiotic resistance. In particular, the section welcomes submissions which support and advance the understanding of resistance mechanisms, development of new antimicrobial drugs, and improvement of patient care and public health, in alignment with SDG 3 (Good Health and Well-being). The Antibiotic Resistance and New Antimicrobial drugs section does not consider studies that lack a direct focus on antibiotic resistance mechanisms, the development of new antimicrobial agents, or the epidemiology of resistant pathogens. Research unrelated to these core topics, such as general microbiology or clinical treatment without a resistance component, falls outside the scope of this section. However, the section welcomes submissions that support and advance the understanding of resistance mechanisms, development of new antimicrobial drugs, and improvement of patient care and public health, in alignment with the goal of promoting good health and well-being. This multidisciplinary section is at the forefront of disseminating and communicating cutting-edge scientific knowledge and impactful discoveries in the field of cellular and infection microbiology to researchers, industry, policymakers, and the public worldwide. | D593: 1440 | E593: Frontiers in Cellular and Infection Microbiology | F593: =VLOOKUP(D593,分野ID!$A$2:$B$49,2,FALSE) -> Cellular and Infection Microbiology
A594: 1486 | B594: Carbon Dioxide Removal | C594: The Carbon Dioxide Removal (CDR) section is dedicated to publishing research focused on strategies and technologies for removing CO2 and other greenhouse gases from the atmosphere. Led by Dr. Phil Renforth from Heriot-Watt University and Dr. Jennifer Wilcox from University of Pennsylvania, the CDR section welcomes submissions in various domains of climate research, which address the challenges and opportunities in achieving climate goals. Topics considered in the scope of this section include: Submissions should provide detailed, in-depth knowledge about the technical, environmental, social, and governance implications of various CDR approaches and methodologies. In particular, the section welcomes submissions which support and advance the carbon dioxide removal, land management-based approaches, climate projections, integrated assessment modeling, geochemical-based approaches, ocean-based approaches, bioenergy with carbon capture and storage, direct air/water capture, and removal of methane and other greenhouse gases (SDG 13: Climate Action, SDG 14: Life Below Water, and SDG 15: Life on Land). The Carbon Dioxide Removal section does not consider submissions that lack a fundamental basis in carbon dioxide or greenhouse gas removal processes. However, studies focused on energy production, climate policy, or other environmental issues may be considered if they have a specific link to removal techniques or contribute to the understanding and advancement of carbon dioxide removal, land management-based approaches, climate projections, integrated assessment modeling, geochemical-based approaches, ocean-based approaches, bioenergy with carbon capture and storage, direct air/water capture, and removal of methane and other greenhouse gases. This multidisciplinary section is at the forefront of disseminating and communicating cutting-edge scientific knowledge and impactful discoveries in the field of climate research to researchers, industry, policymakers, and the public worldwide. | D594: 1490 | E594: Frontiers in Climate | F594: =VLOOKUP(D594,分野ID!$A$2:$B$49,2,FALSE) -> #N/A
A595: 843 | B595: Computer Vision | C595: The Computer Vision section is dedicated to publishing research focused on advancing vision and image analysis technology from a computational perspective. Led by Dr. Marcello Pelillo from Ca' Foscari University of Venice, the Computer Vision section welcomes submissions in various domains of computer vision, which connect fundamental research with practical applications. Topics considered in the scope of this section include: Submissions should provide detailed, in-depth knowledge about the development and application of computer vision and image analysis techniques. The section welcomes submissions which support and advance the SDG: SDG 9: Industry, Innovation and Infrastructure. The Computer Vision section does not consider submissions that lack a strong focus on image or video processing, analysis, and understanding. Studies primarily centered on non-visual data or unrelated hardware development are outside the scope of this section. However, submissions that contribute to the advancement of computer vision techniques and applications, even if not directly related to visual data, may be considered if they support and advance the goals of industry, innovation, and infrastructure. This multidisciplinary section is at the forefront of disseminating and communicating cutting-edge scientific knowledge and impactful discoveries in the field of computer vision to researchers, industry, policymakers, and the public worldwide. | D595: 1511 | E595: Frontiers in Computer Science | F595: =VLOOKUP(D595,分野ID!$A$2:$B$49,2,FALSE) -> Computer Science
A596: 2732 | B596: Thermal Management | C596: The Thermal Management section is dedicated to publishing research focused on advancing knowledge and technology in the field of thermal management. In a world transformed by the Industrial Revolution and now reliant on electronics and electricity, thermal management is crucial for engineered systems. Under the leadership of Prof. Dominic Groulx from Dalhousie University's Department of Mechanical Engineering, we welcome submissions exploring various aspects of thermal engineering. We're particularly interested in research that bridges fundamental studies and practical applications. Topics considered in the scope of this section include: Submissions should provide detailed, in-depth, original, rigorous, and significant research and design work in the field of innovative approaches and advancements in thermal management. Work presenting incremental research improvements will not be accepted in the section. Submissions should provide detailed, in-depth knowledge about these technologies' various aspects. The section specifically welcomes research that aligns with Sustainable Development Goals (SDG): Affordable and Clean Energy (7), Industry, Innovation and Infrastructure (9), and Climate Action(13). This multidisciplinary section is at the forefront of disseminating and communicating cutting-edge scientific knowledge and impactful discoveries in the field of thermal engineering to researchers, industry, policymakers, and the public worldwide. | D596: 2105 | E596: Frontiers in Thermal Engineering | F596: =VLOOKUP(D596,分野ID!$A$2:$B$49,2,FALSE) -> #N/A
A597: 3245 | B597: RNP Biogenesis and Function | C597: The RNP Biogenesis and Function section is dedicated to publishing research focused on the study of ribonucleoprotein (RNP) particles and their role in gene expression. Led by Dr. A. Gregory Matera from the University of North Carolina at Chapel Hill, the RNP Biogenesis and Function section welcomes submissions in the various domains of RNA research, which connect the understanding of RNP assembly, transportation, and function. Topics considered in the scope of this section include: Submissions should provide detailed, in-depth knowledge about the roles of ribonucleoproteins in biological processes. The section welcomes submissions which support and advance the SDG: No SDG applicable. This multidisciplinary section is at the forefront of disseminating and communicating cutting-edge scientific knowledge and impactful discoveries in the field of RNA research to researchers, industry, policymakers, and the public worldwide. | D597: 3189 | E597: Frontiers in RNA Research | F597: =VLOOKUP(D597,分野ID!$A$2:$B$49,2,FALSE) -> #N/A
A598: 797 | B598: Dermatology | C598: The Dermatology section of Frontiers in Medicine publishes research that advances the understanding, diagnosis and treatment of skin and related diseases. Led by Prof. Robert Gniadecki from the University of Alberta, the Dermatology specialty welcomes submissions which synthesise basic, clinical and translational research across the complex array of interactions that the body’s largest organ has with all elements of physical and mental health. Topics considered in-scope for this section include: Research published in the section supports and advances SDG 3: Good Health and Well-being. This multidisciplinary section is at the forefront of disseminating and communicating cutting-edge scientific knowledge and impactful discoveries in the field of Dermatology to researchers, industry, policymakers, and the public worldwide. | D598: 602 | E598: Frontiers in Medicine | F598: =VLOOKUP(D598,分野ID!$A$2:$B$49,2,FALSE) -> Medicine
A599: 3378 | B599: Epigenomic Tools | C599: The Epigenomic Tools section is dedicated to publishing research focused on advancing the understanding of epigenetic processes and their implications in development and diseases. Led by Dr. Ting Wang from Washington University in St. Louis, the Epigenomic Tools section welcomes submissions in the various domains of epigenetics and epigenomics, which aim to enhance the knowledge and application of innovative tools and techniques in the field. Topics considered in the scope of this section include: Submissions should provide detailed, in-depth knowledge about the development and application of tools and resources for investigating epigenetic modification, chromatin organization, and gene regulation. In particular, the section welcomes submissions which support and advance the understanding of epigenetic processes, development of innovative tools and techniques, and their implications in development and diseases (SDG 3: Good Health and Well-being, SDG 9: Industry, Innovation and Infrastructure). This multidisciplinary section is at the forefront of disseminating and communicating cutting-edge scientific knowledge and impactful discoveries in the field of epigenetics and epigenomics to researchers, industry, policymakers, and the public worldwide. | D599: 3032 | E599: Frontiers in Epigenetics and Epigenomics | F599: =VLOOKUP(D599,分野ID!$A$2:$B$49,2,FALSE) -> #N/A
A600: 2494 | B600: Food Policy and Economics | C600: The Food Policy and Economics section is dedicated to publishing research focused on the intersection of nutrition, food policy, and economics. Led by Dr. Igor Pravst from Institute of Nutrition (Slovenia) and Dr. Sean Cash from Gerald J. and Dorothy R. Friedman School of Nutrition Science and Policy, Tufts University, the Food Policy and Economics section welcomes submissions in various domains of food policy and economics, which connect policy and economic aspects of important issues in food and nutrition. Topics considered in the scope of this section include: Submissions should provide detailed, in-depth knowledge about policy and economic aspects of food and nutrition issues. In particular, the section welcomes submissions which support and advance the focus areas of the Section and SDGs, including SDG 2 (Zero Hunger), SDG 3 (Good Health and Well-being), SDG 10 (Reduced Inequalities), SDG 11 (Sustainable Cities and Communities), SDG 12 (Responsible Consumption and Production), and SDG 13 (Climate Action). This multidisciplinary section is at the forefront of disseminating and communicating cutting-edge scientific knowledge and impactful discoveries in the field of food policy and economics to researchers, industry, policymakers, and the public worldwide. | D600: 628 | E600: Frontiers in Nutrition | F600: =VLOOKUP(D600,分野ID!$A$2:$B$49,2,FALSE) -> Nutrition
A601: 1642 | B601: Elections and Representation | C601: The Elections and Representation section is dedicated to publishing research focused on the study of electoral processes and political representation. Led by Dr. Gianfranco Pasquino from SAIS Europe, School of Advanced International Studies, Johns Hopkins University, the Elections and Representation section welcomes submissions in the various domains of electoral studies, which connect theoretical and empirical perspectives to enhance understanding of the field. Topics considered in the scope of this section include: Submissions should provide detailed, in-depth knowledge about the various aspects of elections and political representation, contributing to the advancement of the field. The section welcomes submissions which support and advance the SDG: SDG 16: Peace, Justice and Strong Institutions. The Elections and Representation section does not consider submissions focusing on legal studies, economic development, or population studies, as these topics fall outside the scope of electoral processes and political representation. However, historical analysis may be considered if it is directly related to the study of elections, voting behavior, and representation in a political context. Articles should primarily address issues related to elections and political representation, contributing to the advancement of the field and supporting the goal of promoting peace, justice, and strong institutions. This multidisciplinary section is at the forefront of disseminating and communicating cutting-edge scientific knowledge and impactful discoveries in the field of electoral studies to researchers, industry, policymakers, and the public worldwide. | D601: 1558 | E601: Frontiers in Political Science | F601: =VLOOKUP(D601,分野ID!$A$2:$B$49,2,FALSE) -> Political Science
...

Sheet 分野ID
A1: journal_id | B1: journal_name
A2: 2477 | B2: Aging Neuroscience | C2: aging | D2: section | E2: related | F2: submissions | G2: disease | H2: knowledge | I2: understanding | J2: journal | K2: welcomes | L2: molecular | M2: clinical | N2: brain | O2: diseases | P2: aspects | Q2: cellular | R2: disorders | S2: mechanisms | T2: neuroinflammation | U2: neuroscience | V2: various | W2: conditions | X2: scope | Y2: movement | Z2: considered | AA2: multidisciplinary | AB2: provide | AC2: researchers | AD2: focused | AE2: alzheimer | AF2: dementias | AG2: university | AH2: neurological | AI2: advance | AJ2: health | AK2: fundamental | AL2: disseminating | AM2: communicating | AN2: scientific | AO2: impactful | AP2: discoveries | AQ2: public | AR2: worldwide | AS2: field | AT2: neurocognitive | AU2: behavior | AV2: neuropathy | AW2: associated | AX2: central | AY2: neuronal | AZ2: led
A3: 981 | B3: Applied Mathematics and Statistics | C3: section | D3: mathematical | E3: submissions | F3: systems | G3: knowledge | H3: industry | I3: methods | J3: sdg | K3: science | L3: welcomes | M3: scientific | N3: considered | O3: scope | P3: applications | Q3: field | R3: application | S3: finance | T3: analysis | U3: various | V3: fields | W3: researchers | X3: physics | Y3: mathematics | Z3: data | AA3: dynamical | AB3: topics | AC3: development | AD3: statistical | AE3: should | AF3: statistics | AG3: multidisciplinary | AH3: university | AI3: include | AJ3: support | AK3: advance | AL3: communicating | AM3: public | AN3: biology | AO3: depth | AP3: innovation | AQ3: infrastructure | AR3: computation | AS3: optimization | AT3: led | AU3: computational | AV3: publishing | AW3: focused | AX3: domains | AY3: provide | AZ3: forefront
A4: 1437 | B4: Artificial Intelligence | C4: section | D4: intelligence | E4: submissions | F4: artificial | G4: data | H4: ai | I4: welcomes | J4: industry | K4: knowledge | L4: sdg | M4: public | N4: learning | O4: scope | P4: language | Q4: technology | R4: considered | S4: topics | T4: application | U4: scientific | V4: field | W4: university | X4: support | Y4: big | Z4: advance | AA4: multidisciplinary | AB4: cutting | AC4: edge | AD4: led | AE4: health | AF4: innovation | AG4: communicating | AH4: researchers | AI4: focused | AJ4: various | AK4: domains | AL4: include | AM4: infrastructure | AN4: publishing | AO4: forefront | AP4: disseminating | AQ4: impactful | AR4: discoveries | AS4: policymakers | AT4: worldwide | AU4: dedicated | AV4: should | AW4: provide | AX4: detailed | AY4: depth | AZ4: processing
A5: 603 | B5: Astronomy and Space Sciences | C5: section | D5: physics | E5: submissions | F5: astronomy | G5: knowledge | H5: space | I5: field | J5: scope | K5: various | L5: welcomes | M5: focused | N5: topics | O5: include | P5: scientific | Q5: multidisciplinary | R5: aspects | S5: considered | T5: should | U5: industry | V5: researchers | W5: public | X5: dedicated | Y5: cutting | Z5: edge | AA5: led | AB5: publishing | AC5: forefront | AD5: disseminating | AE5: communicating | AF5: impactful | AG5: discoveries | AH5: policymakers | AI5: worldwide | AJ5: astronomical | AK5: science | AL5: fundamental | AM5: provide | AN5: detailed | AO5: depth | AP5: universe | AQ5: understanding | AR5: domains | AS5: nuclear | AT5: high | AU5: theoretical | AV5: limited | AW5: stellar | AX5: plasma | AY5: sciences | AZ5: areas
A6: 1380 | B6: Big Data | C6: data | D6: section | E6: submissions | F6: big | G6: learning | H6: knowledge | I6: welcomes | J6: industry | K6: intelligence | L6: scope | M6: social | N6: artificial | O6: public | P6: field | Q6: systems | R6: privacy | S6: mining | T6: health | U6: management | V6: topics | W6: machine | X6: advance | Y6: science | Z6: ai | AA6: sdg | AB6: scientific | AC6: analytics | AD6: support | AE6: innovation | AF6: researchers | AG6: focused | AH6: various | AI6: considered | AJ6: led | AK6: university | AL6: include | AM6: infrastructure | AN6: communicating | AO6: address | AP6: impact | AQ6: dedicated | AR6: publishing | AS6: domains | AT6: should | AU6: provide | AV6: detailed | AW6: depth | AX6: application | AY6: consider | AZ6: multidisciplinary
A7: 452 | B7: Bioengineering and Biotechnology | C7: section | D7: submissions | E7: development | F7: biotechnology | G7: welcomes | H7: bioengineering | I7: scope | J7: engineering | K7: topics | L7: considered | M7: health | N7: tissue | O7: applications | P7: application | Q7: articles | R7: various | S7: industry | T7: knowledge | U7: additionally | V7: biological | W7: biomaterials | X7: should | Y7: focused | Z7: systems | AA7: include | AB7: sustainable | AC7: biology | AD7: field | AE7: contribute | AF7: accept | AG7: goals | AH7: good | AI7: innovation | AJ7: bibliometrics | AK7: organ | AL7: biofabrication | AM7: medicine | AN7: synthetic | AO7: led | AP7: sdgs | AQ7: biomedical | AR7: related | AS7: infrastructure | AT7: consider | AU7: outside | AV7: chip | AW7: provide | AX7: regenerative | AY7: university | AZ7: clinical
A8: 755 | B8: Cardiovascular Medicine | C8: section | D8: cardiovascular | E8: submissions | F8: medicine | G8: health | H8: knowledge | I8: scope | J8: disease | K8: welcomes | L8: treatment | M8: field | N8: understanding | O8: sdg | P8: considered | Q8: topics | R8: care | S8: support | T8: heart | U8: scientific | V8: various | W8: good | X8: cardiology | Y8: focused | Z8: researchers | AA8: advance | AB8: public | AC8: consider | AD8: multidisciplinary | AE8: include | AF8: discoveries | AG8: communicating | AH8: should | AI8: publishing | AJ8: forefront | AK8: disseminating | AL8: cutting | AM8: edge | AN8: impactful | AO8: industry | AP8: policymakers | AQ8: worldwide | AR8: clinical | AS8: university | AT8: diseases | AU8: led | AV8: cardiac | AW8: depth | AX8: related | AY8: diagnosis | AZ8: domains
A9: 403 | B9: Cell and Developmental Biology | C9: section | D9: cell | E9: submissions | F9: development | G9: biology | H9: processes | I9: cellular | J9: knowledge | K9: developmental | L9: welcomes | M9: molecular | N9: health | O9: mechanisms | P9: considered | Q9: scope | R9: provide | S9: field | T9: sdg | U9: consider | V9: topics | W9: scientific | X9: public | Y9: should | Z9: various | AA9: gene | AB9: nuclear | AC9: quality | AD9: focused | AE9: understanding | AF9: multidisciplinary | AG9: include | AH9: regulation | AI9: particular | AJ9: biological | AK9: university | AL9: support | AM9: advance | AN9: communicating | AO9: researchers | AP9: industry | AQ9: mechanistic | AR9: organization | AS9: insights | AT9: cancer | AU9: forefront | AV9: disseminating | AW9: cutting | AX9: edge | AY9: impactful | AZ9: discoveries
A10: 1440 | B10: Cellular and Infection Microbiology | C10: section | D10: submissions | E10: health | F10: infection | G10: host | H10: microbiology | I10: welcomes | J10: knowledge | K10: cellular | L10: interactions | M10: university | N10: scope | O10: understanding | P10: infections | Q10: diseases | R10: various | S10: human | T10: focused | U10: topics | V10: considered | W10: microbial | X10: sdg | Y10: public | Z10: infectious | AA10: pathogenesis | AB10: disease | AC10: treatment | AD10: include | AE10: molecular | AF10: development | AG10: good | AH10: provide | AI10: advance | AJ10: clinical | AK10: led | AL10: field | AM10: scientific | AN10: detailed | AO10: depth | AP10: support | AQ10: multidisciplinary | AR10: communicating | AS10: researchers | AT10: dedicated | AU10: publishing | AV10: domains | AW10: should | AX10: mechanisms | AY10: consider | AZ10: forefront
A11: 1523 | B11: Cellular Neuroscience | C11: cellular | D11: section | E11: cells | F11: neuroscience | G11: submissions | H11: journal | I11: mechanisms | J11: functions | K11: neuronal | L11: molecular | M11: function | N11: welcomes | O11: understanding | P11: knowledge | Q11: considered | R11: multidisciplinary | S11: glial | T11: species | U11: university | V11: cell | W11: topics | X11: scope | Y11: frontiers | Z11: neural | AA11: field | AB11: synaptic | AC11: focus | AD11: development | AE11: health | AF11: scientific | AG11: researchers | AH11: neuropathology | AI11: focused | AJ11: brain | AK11: publishing | AL11: nervous | AM11: system | AN11: fundamental | AO11: neurons | AP11: developing | AQ11: sdg | AR11: communicating | AS11: public | AT11: various | AU11: led | AV11: include | AW11: aspects | AX11: signaling | AY11: emergent | AZ11: aging
A12: 601 | B12: Chemistry | C12: section | D12: chemistry | E12: submissions | F12: knowledge | G12: industry | H12: welcomes | I12: chemical | J12: topics | K12: sdg | L12: field | M12: scope | N12: organic | O12: focused | P12: considered | Q12: should | R12: various | S12: provide | T12: applications | U12: materials | V12: advance | W12: scientific | X12: university | Y12: support | Z12: communicating | AA12: researchers | AB12: public | AC12: depth | AD12: multidisciplinary | AE12: molecular | AF12: include | AG12: consider | AH12: forefront | AI12: disseminating | AJ12: cutting | AK12: edge | AL12: impactful | AM12: discoveries | AN12: policymakers | AO12: worldwide | AP12: energy | AQ12: understanding | AR12: sustainable | AS12: publishing | AT12: related | AU12: development | AV12: innovation | AW12: detailed | AX12: science | AY12: aspects | AZ12: infrastructure
A13: 1238 | B13: Communication | C13: communication | D13: section | E13: submissions | F13: health | G13: knowledge | H13: sdg | I13: welcomes | J13: media | K13: cultural | L13: public | M13: scope | N13: topics | O13: industry | P13: field | Q13: various | R13: scientific | S13: aspects | T13: considered | U13: culture | V13: include | W13: language | X13: multidisciplinary | Y13: led | Z13: university | AA13: advance | AB13: creative | AC13: communicating | AD13: researchers | AE13: should | AF13: provide | AG13: support | AH13: cutting | AI13: discoveries | AJ13: industries | AK13: dedicated | AL13: publishing | AM13: focused | AN13: detailed | AO13: depth | AP13: forefront | AQ13: disseminating | AR13: edge | AS13: impactful | AT13: policymakers | AU13: worldwide | AV13: sectors | AW13: organizing | AX13: science | AY13: domains | AZ13: inequalities
... A44: 609 | B44: Public Health | C44: health | D44: section | E44: public | F44: submissions | G44: knowledge | H44: focused | I44: welcomes | J44: considered | K44: sdg | L44: scope | M44: prevention | N44: various | O44: topics | P44: scientific | Q44: focus | R44: prof | S44: field | T44: policy | U44: related | V44: industry | W44: mental | X44: include | Y44: without | Z44: should | AA44: provide | AB44: advance | AC44: support | AD44: inequalities | AE44: multidisciplinary | AF44: led | AG44: communicating | AH44: researchers | AI44: understanding | AJ44: dedicated | AK44: publishing | AL44: domains | AM44: detailed | AN44: depth | AO44: forefront | AP44: disseminating | AQ44: cutting | AR44: edge | AS44: impactful | AT44: discoveries | AU44: policymakers | AV44: worldwide | AW44: good | AX44: medical | AY44: environmental | AZ44: particular
A45: 1213 | B45: Sociology | C45: section | D45: submissions | E45: social | F45: sociology | G45: welcomes | H45: sociological | I45: knowledge | J45: health | K45: gender | L45: public | M45: sdg | N45: understanding | O45: scope | P45: various | Q45: media | R45: topics | S45: migration | T45: field | U45: work | V45: race | W45: inequalities | X45: theory | Y45: considered | Z45: multidisciplinary | AA45: society | AB45: led | AC45: include | AD45: should | AE45: provide | AF45: advance | AG45: ethnicity | AH45: university | AI45: domains | AJ45: aspects | AK45: scientific | AL45: dedicated | AM45: publishing | AN45: focused | AO45: detailed | AP45: depth | AQ45: communicating | AR45: researchers | AS45: support | AT45: sex | AU45: political | AV45: 10 | AW45: reduced | AX45: forefront | AY45: disseminating | AZ45: cutting
A46: 1482 | B46: Sports and Active Living | C46: section | D46: sports | E46: submissions | F46: sport | G46: performance | H46: physical | I46: knowledge | J46: exercise | K46: welcomes | L46: health | M46: scope | N46: aspects | O46: sdg | P46: considered | Q46: various | R46: activity | S46: topics | T46: focused | U46: multidisciplinary | V46: field | W46: include | X46: researchers | Y46: public | Z46: industry | AA46: prevention | AB46: led | AC46: scientific | AD46: sciences | AE46: policymakers | AF46: communicating | AG46: dedicated | AH46: focus | AI46: education | AJ46: management | AK46: publishing | AL46: domains | AM46: provide | AN46: should | AO46: cutting | AP46: edge | AQ46: impactful | AR46: discoveries | AS46: worldwide | AT46: science | AU46: university | AV46: detailed | AW46: depth | AX46: consider | AY46: forefront | AZ46: disseminating
A47: 649 | B47: Veterinary Science | C47: section | D47: veterinary | E47: submissions | F47: animal | G47: health | H47: medicine | I47: knowledge | J47: welcomes | K47: sdg | L47: animals | M47: scope | N47: considered | O47: focused | P47: topics | Q47: human | R47: various | S47: scientific | T47: field | U47: diseases | V47: understanding | W47: advance | X47: life | Y47: researchers | Z47: should | AA47: university | AB47: clinical | AC47: public | AD47: consider | AE47: disease | AF47: led | AG47: include | AH47: domains | AI47: support | AJ47: communicating | AK47: provide | AL47: detailed | AM47: depth | AN47: multidisciplinary | AO47: cutting | AP47: edge | AQ47: discoveries | AR47: worldwide | AS47: dedicated | AT47: publishing | AU47: forefront | AV47: disseminating | AW47: impactful | AX47: industry | AY47: good | AZ47: policymakers
A48: 1561 | B48: Virtual Reality | C48: reality | D48: virtual | E48: section | F48: submissions | G48: industry | H48: augmented | I48: welcomes | J48: sdg | K48: knowledge | L48: technologies | M48: human | N48: scope | O48: behaviour | P48: considered | Q48: field | R48: scientific | S48: topics | T48: technology | U48: multidisciplinary | V48: led | W48: university | X48: support | Y48: advance | Z48: innovation | AA48: infrastructure | AB48: communicating | AC48: researchers | AD48: public | AE48: application | AF48: dedicated | AG48: publishing | AH48: focused | AI48: various | AJ48: domains | AK48: include | AL48: should | AM48: provide | AN48: detailed | AO48: depth | AP48: forefront | AQ48: disseminating | AR48: cutting | AS48: edge | AT48: impactful | AU48: discoveries | AV48: policymakers | AW48: worldwide | AX48: applications | AY48: development | AZ48: advancements
A49: 1451 | B49: Water | C49: water | D49: section | E49: submissions | F49: climate | G49: resources | H49: human | I49: welcomes | J49: knowledge | K49: systems | L49: scope | M49: management | N49: understanding | O49: various | P49: topics | Q49: hydrological | R49: health | S49: scientific | T49: clean | U49: sanitation | V49: industry | W49: quality | X49: environmental | Y49: multidisciplinary | Z49: field | AA49: sustainable | AB49: zone | AC49: action | AD49: environment | AE49: led | AF49: domains | AG49: particular | AH49: support | AI49: advance | AJ49: challenges | AK49: communicating | AL49: researchers | AM49: public | AN49: critical | AO49: focused | AP49: processes | AQ49: considered | AR49: address | AS49: university | AT49: related | AU49: dedicated | AV49: publishing | AW49: include | AX49: provide | AY49: change | AZ49: consider

Sheet about_domain
A1: DomainId | B1: Title | C1: Text | D1: flag
A2: 1532 | B2: Frontiers in Chemical Engineering | C2: Frontiers in Chemical Engineering is a multidisciplinary, DOAJ and Web of Science (ESCI) indexed journal that publishes high-impact research on all aspects of chemical engineering. Led by Field Chief Editor Prof Fengqi You (Cornell University, USA), the journal publishes fundamental and applied research related to chemical engineering aspects ranging across disciplines and scales, from the molecular level to the plant level, with a wider impact on global issues. Topics of interest include, but are not limited to: While there are many subtopics and specialties of chemical engineering, collaborative research across all specialty areas of chemical engineering is highly encouraged and supported. Modern chemical engineering spearheads new developments in energy systems, environmental solutions, medicine, biotechnology, microelectronics, advanced materials, consumer products, and manufacturing, by intimately linking with the fundamental subjects of chemistry, physics, biology, mathematics, and economics, and in close collaboration with fellow engineering disciplines like computer science, materials science, and mechanical, electrical, and civil engineering. Frontiers in Chemical Engineering is committed to advancing developments in the field of chemical engineering by allowing unrestricted access to articles, and communicating scientific knowledge to researchers and the public alike, to enable the scientific breakthroughs of the future. | D2: =VLOOKUP(A2,分野ID!$A$2:$B$49,2,FALSE) -> #N/A
A3: 6 | B3: Frontiers in Integrative Neuroscience | C3: Frontiers in Integrative Neuroscience publishes research that synthesizes multiple facets of brain-body structure and function, to better understand how multiple diverse functions are integrated to produce complex behaviors. Led by Specialty Chief Editor Prof Elizabeth B Torres (Rutgers University, USA) and indexed in PubMed Central (PMC), Scopus, and the DOAJ, the journal publishes research that furthers our understanding of the integrative mechanisms underlying brain-body functioning across one or more interacting levels of neural organization. Topics of interest include, but are not limited to: Research in any species and at any stage of development and aging that is focused on understanding integration mechanisms underlying emergent properties of the brain-body and behavior are welcome. The journal also encourages submissions which support and advance the UN’s Sustainable Development Goals (SDGs), notably SDG 3: ensuring healthy lives and well-being for all at all ages. Manuscripts that focus on alternative medicine or processes that do not have a fundamental basis in neuroscience are not suitable for publication in this journal. Frontiers in Integrative Neuroscience is committed to advancing developments in the field by allowing unrestricted access to articles and communicating scientific knowledge to researchers and the public alike, to enable the scientific breakthroughs of the future. | D3: =VLOOKUP(A3,分野ID!$A$2:$B$49,2,FALSE) -> #N/A
A4: 3135 | B4: Frontiers in Medical Engineering | C4: Frontiers in Medical Engineering is a multidisciplinary journal that focuses on the development of engineering solutions in medicine and healthcare. Led by Field Chief Editor Prof. Dominique P. Pioletti (Swiss Federal Institute of Technology Lausanne, Switzerland), Frontiers in Medical Engineering is a DOAJ-indexed journal welcoming research contributions in the various domains of medical engineering, which bridge the gap between engineering concepts and medical applications. Topics include, but are not limited to: In particular, the journal welcomes submissions covering the development of sophisticated imaging equipment, nanorobotics for molecular-level tasks, understanding organ systems for therapy development, engineering and biological approaches to therapies, and artificial intelligence in diagnostics and therapeutics. The journal supports and advances the Sustainable Development Goals (SDGs), specifically SDG 3: Good Health and Well-Being. Medical engineering plays a crucial role in advancing healthcare solutions, improving medical diagnostics, and developing innovative therapies to ensure healthy lives and promote well-being for all at all ages. By fostering interdisciplinary collaboration among scientists, engineers, and medical professionals, the journal promotes research and development in medical engineering, ultimately leading to better health outcomes and improved quality of life for individuals worldwide. Manuscripts relating to topics not directly connected to medical engineering, such as those focusing solely on the development and testing of the technology within the field, are not suitable for publication in this journal and should instead be submitted to Frontiers in Medical Technology. Frontiers in Medical Engineering is committed to advancing developments in the field of medical engineering by allowing unrestricted access to articles and communicating scientific knowledge to researchers and the public alike, to enable the scientific breakthroughs of the future. | D4: =VLOOKUP(A4,分野ID!$A$2:$B$49,2,FALSE) -> #N/A
A5: 921 | B5: Frontiers in Built Environment | C5: Frontiers in Built Environment is a multidisciplinary journal that focuses on the development of smart and sustainable methodologies for the design, construction and management of resilient buildings and infrastructure. Led by Field Chief Editor Prof Izuru Takewaki (Kyoto Arts and Crafts University, Japan), the journal welcomes submissions in all areas of built environment research across all areas of civil engineering, within and beyond urban spaces. It is currently indexed in DOAJ, Scopus, and Web of Science (ESCI) among others. The journal covers the following subject areas: In addition, submissions in the following areas are encouraged: In particular, the journal welcomes submissions which support and advance the UN’s Sustainable Development Goals (SDGs), notably SDG 9: industry, innovation, and infrastructure. Manuscripts that focus solely on climate change, human growth, education, or industry without a fundamental basis in the built environment are not suitable for publication in this journal. Additionally, studies that are purely engineering in nature, without considering the broader implications for the built environment, are also outside the journal's scope. Frontiers in Built Environment is committed to advancing developments in the field by communicating scientific knowledge to researchers and the public alike, to enable the scientific breakthroughs of the future. | D5: =VLOOKUP(A5,分野ID!$A$2:$B$49,2,FALSE) -> #N/A
A6: 2136 | B6: Frontiers in Drug Delivery | C6: Frontiers in Drug Delivery is a multidisciplinary, DOAJ-indexed journal that focuses on drug delivery concepts at a cell and tissue level, through to translational outcomes in preclinical and clinical studies for drug formulations and formulations combined with devices. The journal is led by Field Chief Editor Prof David Brayden (University College Dublin, Ireland) and welcomes submissions in all areas of drug delivery research focusing on key delivery routes as well as on important specific disease or product areas where delivery can play an important role. The following subject areas are covered: Submissions from the following research areas are also encouraged: In particular, the journal welcomes submissions which support and advance the UN’s Sustainable Development Goals (SDGs), notably SDG 3: good health and well-being. Manuscripts purely relating to drug discovery that is not associated with delivery aspects are not suitable for publication in this journal. Frontiers in Drug Delivery is committed to advancing developments in the field of drug delivery by communicating scientific knowledge to researchers and the public alike, to enable the scientific breakthroughs of the future. | D6: =VLOOKUP(A6,分野ID!$A$2:$B$49,2,FALSE) -> #N/A
A7: 602 | B7: Frontiers in Medicine | C7: Frontiers in Medicine is a broad-scope, multidisciplinary journal covering all established medical disciplines to improve clinical practice and patient care. Led by Field Chief Editor Prof Michel Goldman (Université libre de Bruxelles, Belgium), Frontiers in Medicine is indexed in PubMed Central (PMC), Web of Science (SCIE), and Scopus, among others, and welcomes basic and clinical medical research that facilitate the translation of scientific advances into new therapies or diagnostic tools. Topics include, but are not limited to: In addition to papers that provide a link between basic research and clinical practice, a particular emphasis is given to studies that are directly relevant to patient care. As well as the established medical disciplines, Frontiers in Medicine aims to publish research that will facilitate: All studies must contribute insights into the field of medicine. Papers which do not primarily focus on a medical discipline are not suitable for publication in this journal. Manuscripts that focus solely on the molecular or cellular mechanisms of diseases without a foundation in clinical medicine are not suitable for publication in this journal. Similarly, studies that are purely descriptive or observational, without a clear hypothesis or mechanistic investigation, are not within the scope of this journal. Research that is primarily epidemiological or public health-oriented, without a foundation in the pathophysiology or treatment of disease, is also not appropriate for this journal. Frontiers in Medicine is committed to advancing developments in the field of medicine by allowing unrestricted access to articles and communicating scientific knowledge to researchers and the public alike, to enable the scientific breakthroughs of the future. Ethics Statement: All manuscripts submitted to Frontiers in Medicine that have been conducted in human subjects must conform with current regulations and the Declaration of Helsinki. Ethics committee approval and informed patient consent are required for studies involving human subjects. Ethics committee approval is also needed for studies involving animals. Phase I - Phase IV clinical trials submitted for publication in Frontiers in Medicine must have been registered with an appropriate public trials registry at the time or before the first patient enrolment. The information on the clinical trial registration (Unique Identifier and URL) must be included in the abstract. Authors are required to disclose all apparent or potential conflicts of interest according to the ICMJE guidelines and those of Frontiers. Frontiers endeavors to follow the guidelines and best practice recommendations published by the Committee on Publication Ethics (COPE). Authors should refer to the author guidelines for full details. | D7: =VLOOKUP(A7,分野ID!$A$2:$B$49,2,FALSE) -> Medicine
A8: 3381 | B8: Frontiers in Synthetic Biology | C8: Frontiers in Synthetic Biology is an interdisciplinary field that encompasses research, engineering, and technoscience. Its fundamental premise is that living cells, tissues, and organisms can be regarded as miniature programmable production units. In this analogy, DNA functions as the software that governs the synthesis of proteins, metabolites, and various small and complex molecules, collectively akin to its hardware. Realizing these objectives requires the integration of diverse disciplines, including biological, chemical, software, and mechatronic engineering. It also draws on fundamental sciences such as chemistry, biology, statistics, artificial intelligence, and biophysics, all converging under the umbrella of synthetic biology. Led by Field Chief Editor Ned Budisa from the University of Manitoba, Frontiers in Synthetic Biology understands the significance of being an open-access publisher and aims to contribute positively to the widespread dissemination of research in synthetic biology by bridging the gap between bioengineering, industrial research, and basic sciences, leveraging the interdisciplinary nature of the field. The journal aims to encompass various topics, including: The journal welcomes high-quality submissions that support and advance research conducted on both in vitro platforms, including microfluidic devices with a particular emphasis on bottom-up synthetic biology, as well as in vivo studies encompassing viruses, bacteria, mammals, plants, and animals in laboratory settings or environmental contexts. We recognize the significance of the integration of biology and digital technologies, which we anticipate will be a major focal point for humanity in the coming decades. This encompasses theoretical and in silico papers that present novel models, tools, and concepts, along with scientific proof-of-principle demonstrations and bioengineering advancements. Special perspective articles will be dedicated to iGEM student teams, companies, and observers from various fields, particularly the social sciences, providing a valuable resource for students and scholars interested in exploring the educational, industrial, and societal dimensions and implications of synthetic biology. Considering the inherent interdisciplinarity of synthetic biology, which often blurs the boundaries with other related research areas and biotechnology, we acknowledge the challenge of clearly differentiating it. To address this, we will foster close collaborations with Frontiers sister journals. This collaborative approach will ensure that we work together to minimize any potential overlap in research coverage, thereby optimizing the publication landscape in the field of synthetic biology. | D8: =VLOOKUP(A8,分野ID!$A$2:$B$49,2,FALSE) -> #N/A
